{
    "events": [
        {
            "year": 217,
            "html": "<a href=\"https://wikipedia.org/wiki/Roman_emperor\" title=\"Roman emperor\">Roman emperor</a> <a href=\"https://wikipedia.org/wiki/Caracalla\" title=\"Caracalla\">Caracalla</a> is assassinated and is succeeded by his <a href=\"https://wikipedia.org/wiki/Praetorian_Guard\" title=\"Praetorian Guard\">Praetorian Guard</a> <a href=\"https://wikipedia.org/wiki/Prefect\" title=\"Prefect\">prefect</a>, <a href=\"https://wikipedia.org/wiki/Marcus_Opellius_Macrinus\" title=\"Marcus Opellius Macrinus\">Marcus Opellius Macrinus</a>."
        },
        {
            "year": 876,
            "html": "The <a href=\"https://wikipedia.org/wiki/Battle_of_Dayr_al-%27Aqul\" title=\"Battle of Dayr al-'Aqul\">Battle of Dayr al-'Aqul</a> saves <a href=\"https://wikipedia.org/wiki/Baghdad\" title=\"Baghdad\">Baghdad</a> from the <a href=\"https://wikipedia.org/wiki/Saffarids\" title=\"Saffarids\">Saffarids</a>."
        },
        {
            "year": 1139,
            "html": "<a href=\"https://wikipedia.org/wiki/Roger_II_of_Sicily\" title=\"Roger II of Sicily\">Roger II of Sicily</a> is excommunicated by <a href=\"https://wikipedia.org/wiki/Innocent_II\" title=\"Innocent II\">Innocent II</a> for supporting <a href=\"https://wikipedia.org/wiki/Antipope_Anacletus_II\" title=\"Antipope Anacletus II\">Anacletus II</a> as <a href=\"https://wikipedia.org/wiki/Pope\" title=\"Pope\">pope</a> for seven years, even though Roger had already publicly recognized Innocent's claim to the papacy."
        },
        {
            "year": 1232,
            "html": "<a href=\"https://wikipedia.org/wiki/Mongol_conquest_of_the_Jin_dynasty\" title=\"Mongol conquest of the Jin dynasty\">Mongol-Jin War</a>: The <a href=\"https://wikipedia.org/wiki/Mongol_Empire\" title=\"Mongol Empire\">Mongols</a> begin their <a href=\"https://wikipedia.org/wiki/Mongol_siege_of_Kaifeng\" title=\"Mongol siege of Kaifeng\">siege on Kaifeng</a>, the capital of the <a href=\"https://wikipedia.org/wiki/Jin_dynasty_(1115%E2%80%931234)\" title=\"Jin dynasty (1115-1234)\">Jin dynasty</a>."
        },
        {
            "year": 1250,
            "html": "<a href=\"https://wikipedia.org/wiki/Seventh_Crusade\" title=\"Seventh Crusade\">Seventh Crusade</a>: <a href=\"https://wikipedia.org/wiki/Ayyubid_dynasty\" title=\"Ayyubid dynasty\">Ayyubids</a> of Egypt capture King <a href=\"https://wikipedia.org/wiki/Louis_IX_of_France\" title=\"Louis IX of France\">Louis IX of France</a> in the <a href=\"https://wikipedia.org/wiki/Battle_of_Fariskur_(1250)\" title=\"Battle of Fariskur (1250)\">Battle of Fariskur</a>."
        },
        {
            "year": 1271,
            "html": "In <a href=\"https://wikipedia.org/wiki/Syria\" title=\"Syria\">Syria</a>, sultan <a href=\"https://wikipedia.org/wiki/Baibars\" title=\"Baibars\">Baibars</a> conquers the <a href=\"https://wikipedia.org/wiki/Krak_des_Chevaliers\" title=\"Krak des Chevaliers\">Krak des Chevaliers</a>."
        },
        {
            "year": 1605,
            "html": "The city of <a href=\"https://wikipedia.org/wiki/Oulu\" title=\"Oulu\">Oulu</a>, <a href=\"https://wikipedia.org/wiki/Finland\" title=\"Finland\">Finland</a>, is founded by <a href=\"https://wikipedia.org/wiki/Charles_IX_of_Sweden\" title=\"Charles IX of Sweden\">Charles IX of Sweden</a>."
        },
        {
            "year": 1730,
            "html": "<a href=\"https://wikipedia.org/wiki/Congregation_Shearith_Israel\" title=\"Congregation Shearith Israel\">Shearith Israel</a>, the first <a href=\"https://wikipedia.org/wiki/Synagogue\" title=\"Synagogue\">synagogue</a> in continental North America, is dedicated."
        },
        {
            "year": 1812,
            "html": "Czar <a href=\"https://wikipedia.org/wiki/Alexander_I_of_Russia\" title=\"Alexander I of Russia\">Alexander I</a>, the <a href=\"https://wikipedia.org/wiki/Emperor_of_Russia\" title=\"Emperor of Russia\">Russian Emperor</a> and the <a href=\"https://wikipedia.org/wiki/Grand_Duke_of_Finland\" title=\"Grand Duke of Finland\">Grand Duke of Finland</a>, officially announces the transfer of the status of the Finnish capital from <a href=\"https://wikipedia.org/wiki/Turku\" title=\"Turku\">Turku</a> to <a href=\"https://wikipedia.org/wiki/Helsinki\" title=\"Helsinki\">Helsinki</a>."
        },
        {
            "year": 1820,
            "html": "The <i><a href=\"https://wikipedia.org/wiki/Venus_de_Milo\" title=\"Venus de Milo\">Venus de Milo</a></i> is discovered on the <a href=\"https://wikipedia.org/wiki/Aegean_Sea\" title=\"Aegean Sea\">Aegean</a> island of <a href=\"https://wikipedia.org/wiki/Milos\" title=\"Milos\">Milos</a>."
        },
        {
            "year": 1832,
            "html": "<a href=\"https://wikipedia.org/wiki/Black_Hawk_War\" title=\"Black Hawk War\">Black Hawk War</a>: Around 300 United States 6th Infantry troops leave <a href=\"https://wikipedia.org/wiki/St._Louis,_Missouri\" title=\"St. Louis, Missouri\">St. Louis, Missouri</a> to fight the <a href=\"https://wikipedia.org/wiki/Sauk_people\" title=\"Sauk people\">Sauk</a> <a href=\"https://wikipedia.org/wiki/Native_Americans_in_the_United_States\" title=\"Native Americans in the United States\">Native Americans</a>."
        },
        {
            "year": 1866,
            "html": "<a href=\"https://wikipedia.org/wiki/Austro-Prussian_War\" title=\"Austro-Prussian War\">Austro-Prussian War</a>: <a href=\"https://wikipedia.org/wiki/Italy\" title=\"Italy\">Italy</a> and <a href=\"https://wikipedia.org/wiki/Prussia\" title=\"Prussia\">Prussia</a> sign a secret alliance against the <a href=\"https://wikipedia.org/wiki/Austrian_Empire\" title=\"Austrian Empire\">Austrian Empire</a>."
        },
        {
            "year": 1886,
            "html": "<a href=\"https://wikipedia.org/wiki/William_Ewart_Gladstone\" title=\"William Ewart Gladstone\">William Ewart Gladstone</a> introduces the first <a href=\"https://wikipedia.org/wiki/Irish_Government_Bill_1886\" title=\"Irish Government Bill 1886\">Irish Home Rule Bill</a> into the <a href=\"https://wikipedia.org/wiki/House_of_Commons_of_the_United_Kingdom\" title=\"House of Commons of the United Kingdom\">British House of Commons</a>."
        },
        {
            "year": 1895,
            "html": "In <i><a href=\"https://wikipedia.org/wiki/Pollock_v._Farmers%27_Loan_%26_Trust_Co.\" title=\"Pollock v. Farmers' Loan &amp; Trust Co.\">Pollock v. Farmers' Loan &amp; Trust Co.</a></i> the <a href=\"https://wikipedia.org/wiki/Supreme_Court_of_the_United_States\" title=\"Supreme Court of the United States\">Supreme Court of the United States</a> declares unapportioned <a href=\"https://wikipedia.org/wiki/Income_tax_in_the_United_States\" title=\"Income tax in the United States\">income tax</a> to be <a href=\"https://wikipedia.org/wiki/Constitutionality\" title=\"Constitutionality\">unconstitutional</a>."
        },
        {
            "year": 1904,
            "html": "The <a href=\"https://wikipedia.org/wiki/French_Third_Republic\" title=\"French Third Republic\">French Third Republic</a> and the <a href=\"https://wikipedia.org/wiki/United_Kingdom_of_Great_Britain_and_Ireland\" title=\"United Kingdom of Great Britain and Ireland\">United Kingdom of Great Britain and Ireland</a> sign the <i><a href=\"https://wikipedia.org/wiki/Entente_cordiale\" title=\"Entente cordiale\">Entente cordiale</a></i>."
        },
        {
            "year": 1906,
            "html": "<a href=\"https://wikipedia.org/wiki/Auguste_Deter\" title=\"Auguste Deter\">Auguste Deter</a>, the first person to be diagnosed with <a href=\"https://wikipedia.org/wiki/Alzheimer%27s_disease\" title=\"Alzheimer's disease\">Alzheimer's disease</a>, dies."
        },
        {
            "year": 1908,
            "html": "<a href=\"https://wikipedia.org/wiki/Harvard_University\" title=\"Harvard University\">Harvard University</a> votes to establish the <a href=\"https://wikipedia.org/wiki/Harvard_Business_School\" title=\"Harvard Business School\">Harvard Business School</a>."
        },
        {
            "year": 1911,
            "html": "<a href=\"https://wikipedia.org/wiki/Dutch_people\" title=\"Dutch people\">Dutch</a> physicist <a href=\"https://wikipedia.org/wiki/Heike_Kamerlingh_Onnes\" title=\"Heike Kamerlingh Onnes\">Heike Kamerlingh Onnes</a> discovers <a href=\"https://wikipedia.org/wiki/Superconductivity\" title=\"Superconductivity\">superconductivity</a>."
        },
        {
            "year": 1913,
            "html": "The <a href=\"https://wikipedia.org/wiki/17th_Amendment_to_the_United_States_Constitution\" title=\"17th Amendment to the United States Constitution\">17th Amendment to the United States Constitution</a>, requiring direct <a href=\"https://wikipedia.org/wiki/Election\" title=\"Election\">election</a> of <a href=\"https://wikipedia.org/wiki/United_States_Senate\" title=\"United States Senate\">Senators</a>, becomes law."
        },
        {
            "year": 1918,
            "html": "<a href=\"https://wikipedia.org/wiki/World_War_I\" title=\"World War I\">World War I</a>: Actors <a href=\"https://wikipedia.org/wiki/Douglas_Fairbanks\" title=\"Douglas Fairbanks\">Douglas Fairbanks</a> and <a href=\"https://wikipedia.org/wiki/Charlie_Chaplin\" title=\"Charlie Chaplin\">Charlie Chaplin</a> sell <a href=\"https://wikipedia.org/wiki/War_bond\" title=\"War bond\">war bonds</a> on the streets of New York City's financial district."
        },
        {
            "year": 1924,
            "html": "<a href=\"https://wikipedia.org/wiki/Sharia\" title=\"Sharia\">Sharia</a> courts are abolished in <a href=\"https://wikipedia.org/wiki/Turkey\" title=\"Turkey\">Turkey</a>, as part of <a href=\"https://wikipedia.org/wiki/Atat%C3%BCrk%27s_Reforms\" title=\"Atatürk's Reforms\">Atatürk's Reforms</a>."
        },
        {
            "year": 1929,
            "html": "<a href=\"https://wikipedia.org/wiki/Indian_independence_movement\" title=\"Indian independence movement\">Indian independence movement</a>: At the Delhi Central Assembly, <a href=\"https://wikipedia.org/wiki/Bhagat_Singh\" title=\"Bhagat Singh\">Bhagat Singh</a> and <a href=\"https://wikipedia.org/wiki/Batukeshwar_Dutt\" title=\"Batukeshwar Dutt\">Batukeshwar Dutt</a> throw handouts and bombs to court arrest."
        },
        {
            "year": 1935,
            "html": "The <a href=\"https://wikipedia.org/wiki/Works_Progress_Administration\" title=\"Works Progress Administration\">Works Progress Administration</a> is formed when the <a href=\"https://wikipedia.org/wiki/Emergency_Relief_Appropriation_Act_of_1935\" title=\"Emergency Relief Appropriation Act of 1935\">Emergency Relief Appropriation Act of 1935</a> becomes law."
        },
        {
            "year": 1940,
            "html": "The Central Committee of the <a href=\"https://wikipedia.org/wiki/Mongolian_People%27s_Party\" title=\"Mongolian People's Party\">Mongolian People's Revolutionary Party</a> elects <a href=\"https://wikipedia.org/wiki/Yumjaagiin_Tsedenbal\" title=\"Yumjaagiin Tsedenbal\">Yumjaagiin Tsedenbal</a> as <a href=\"https://wikipedia.org/wiki/General_Secretary_of_the_Mongolian_People%27s_Party\" title=\"General Secretary of the Mongolian People's Party\">General Secretary</a>, marking the beginning of his 44-year-long tenure as <i>de facto</i> leader of <a href=\"https://wikipedia.org/wiki/Mongolian_People%27s_Republic\" title=\"Mongolian People's Republic\">Mongolia</a>."
        },
        {
            "year": 1942,
            "html": "<a href=\"https://wikipedia.org/wiki/World_War_II\" title=\"World War II\">World War II</a>: The <a href=\"https://wikipedia.org/wiki/Empire_of_Japan\" title=\"Empire of Japan\">Japanese</a> take <a href=\"https://wikipedia.org/wiki/Bataan\" title=\"Bataan\">Bataan</a> in the <a href=\"https://wikipedia.org/wiki/Philippines\" title=\"Philippines\">Philippines</a>."
        },
        {
            "year": 1943,
            "html": "U.S. President <a href=\"https://wikipedia.org/wiki/Franklin_D._Roosevelt\" title=\"Franklin D. Roosevelt\">Franklin D. Roosevelt</a>, in an attempt to check <a href=\"https://wikipedia.org/wiki/Inflation\" title=\"Inflation\">inflation</a>, freezes wages and prices, prohibits workers from changing jobs unless the war effort would be aided thereby, and bars rate increases by <a href=\"https://wikipedia.org/wiki/Common_carrier\" title=\"Common carrier\">common carriers</a> and <a href=\"https://wikipedia.org/wiki/Public_utilities\" title=\"Public utilities\">public utilities</a>."
        },
        {
            "year": 1943,
            "html": "<a href=\"https://wikipedia.org/wiki/Otto_and_Elise_Hampel\" title=\"Otto and Elise Hampel\">Otto and Elise Hampel</a> are executed in <a href=\"https://wikipedia.org/wiki/Berlin\" title=\"Berlin\">Berlin</a> for their anti-Nazi activities."
        },
        {
            "year": 1945,
            "html": "World War II: After an air raid accidentally destroys a train carrying about 4,000 <a href=\"https://wikipedia.org/wiki/Nazi_concentration_camp\" title=\"Nazi concentration camp\">Nazi concentration camp</a> internees in <a href=\"https://wikipedia.org/wiki/Prussian_Hanover\" title=\"Prussian Hanover\">Prussian Hanover</a>, the survivors are <a href=\"https://wikipedia.org/wiki/Celler_Hasenjagd\" title=\"Celler Hasenjagd\">massacred</a> by Nazis."
        },
        {
            "year": 1946,
            "html": "<a href=\"https://wikipedia.org/wiki/%C3%89lectricit%C3%A9_de_France\" title=\"Électricité de France\">Électricité de France</a>, the world's largest <a href=\"https://wikipedia.org/wiki/Utility_company\" title=\"Utility company\">utility company</a>, is formed as a result of the <a href=\"https://wikipedia.org/wiki/Nationalisation\" title=\"Nationalisation\">nationalisation</a> of a number of electricity producers, transporters and distributors."
        },
        {
            "year": 1950,
            "html": "<a href=\"https://wikipedia.org/wiki/India\" title=\"India\">India</a> and <a href=\"https://wikipedia.org/wiki/Pakistan\" title=\"Pakistan\">Pakistan</a> sign the <a href=\"https://wikipedia.org/wiki/Liaquat%E2%80%93Nehru_Pact\" title=\"Liaquat-Nehru Pact\">Liaquat-Nehru Pact</a>."
        },
        {
            "year": 1952,
            "html": "U.S. President <a href=\"https://wikipedia.org/wiki/Harry_Truman\" title=\"Harry Truman\">Harry Truman</a> calls for the seizure of all domestic steel mills in an attempt to prevent the <a href=\"https://wikipedia.org/wiki/1952_steel_strike\" title=\"1952 steel strike\">1952 steel strike</a>."
        },
        {
            "year": 1953,
            "html": "<a href=\"https://wikipedia.org/wiki/Mau_Mau_rebellion\" title=\"Mau Mau rebellion\">Mau Mau</a> leader <a href=\"https://wikipedia.org/wiki/Jomo_Kenyatta\" title=\"Jomo Kenyatta\">Jomo Kenyatta</a> is convicted by <a href=\"https://wikipedia.org/wiki/British_Kenya\" title=\"British Kenya\">British Kenya</a>'s rulers."
        },
        {
            "year": 1954,
            "html": "A Royal Canadian Air Force Canadair <a href=\"https://wikipedia.org/wiki/T-6_Texan\" title=\"T-6 Texan\">Harvard</a> collides with a <a href=\"https://wikipedia.org/wiki/Trans-Canada_Air_Lines\" title=\"Trans-Canada Air Lines\">Trans-Canada Airlines</a> <a href=\"https://wikipedia.org/wiki/Canadair_North_Star\" title=\"Canadair North Star\">Canadair North Star</a> over <a href=\"https://wikipedia.org/wiki/Moose_Jaw,_Saskatchewan\" title=\"Moose Jaw, Saskatchewan\">Moose Jaw, Saskatchewan</a>, killing 37 people."
        },
        {
            "year": 1954,
            "html": "<a href=\"https://wikipedia.org/wiki/South_African_Airways_Flight_201\" title=\"South African Airways Flight 201\">South African Airways Flight 201</a> A <a href=\"https://wikipedia.org/wiki/De_Havilland_Comet\" title=\"De Havilland Comet\">de Havilland DH.106 Comet 1</a> crashes into the sea during night killing 21 people."
        },
        {
            "year": 1959,
            "html": "A team of computer manufacturers, users, and university people led by <a href=\"https://wikipedia.org/wiki/Grace_Hopper\" title=\"Grace Hopper\">Grace Hopper</a> meets to discuss the creation of a new <a href=\"https://wikipedia.org/wiki/Programming_language\" title=\"Programming language\">programming language</a> that would be called <a href=\"https://wikipedia.org/wiki/COBOL\" title=\"COBOL\">COBOL</a>."
        },
        {
            "year": 1959,
            "html": "The <a href=\"https://wikipedia.org/wiki/Organization_of_American_States\" title=\"Organization of American States\">Organization of American States</a> drafts an agreement to create the <a href=\"https://wikipedia.org/wiki/Inter-American_Development_Bank\" title=\"Inter-American Development Bank\">Inter-American Development Bank</a>."
        },
        {
            "year": 1960,
            "html": "The <a href=\"https://wikipedia.org/wiki/Netherlands\" title=\"Netherlands\">Netherlands</a> and <a href=\"https://wikipedia.org/wiki/West_Germany\" title=\"West Germany\">West Germany</a> sign an agreement to negotiate the return of <a href=\"https://wikipedia.org/wiki/Dutch_annexation_of_German_territory_after_World_War_II\" title=\"Dutch annexation of German territory after World War II\">German land annexed by the Dutch</a> in return for 280 million <a href=\"https://wikipedia.org/wiki/German_mark\" title=\"German mark\">German marks</a> as <a href=\"https://wikipedia.org/wiki/Wiedergutmachung\" title=\"Wiedergutmachung\">Wiedergutmachung</a>."
        },
        {
            "year": 1968,
            "html": "<a href=\"https://wikipedia.org/wiki/BOAC_Flight_712\" title=\"BOAC Flight 712\">BOAC Flight 712</a> catches fire shortly after takeoff. As a result of her actions in the accident, <a href=\"https://wikipedia.org/wiki/Barbara_Jane_Harrison\" title=\"Barbara Jane Harrison\">Barbara Jane Harrison</a> is awarded a posthumous <a href=\"https://wikipedia.org/wiki/George_Cross\" title=\"George Cross\">George Cross</a>, the only GC awarded to a woman in peacetime."
        },
        {
            "year": 1970,
            "html": "<a href=\"https://wikipedia.org/wiki/Bahr_El-Baqar_primary_school_bombing\" title=\"Bahr El-Baqar primary school bombing\">Bahr El-Baqar primary school bombing</a>: Israeli bombers accidentally strike an Egyptian school. Forty-six children are killed."
        },
        {
            "year": 1975,
            "html": "<a href=\"https://wikipedia.org/wiki/Frank_Robinson\" title=\"Frank Robinson\">Frank Robinson</a> manages the <a href=\"https://wikipedia.org/wiki/Cleveland_Indians\" title=\"Cleveland Indians\">Cleveland Indians</a> in his first game as major league <a href=\"https://wikipedia.org/wiki/Baseball\" title=\"Baseball\">baseball</a>'s first <a href=\"https://wikipedia.org/wiki/African_American\" title=\"African American\">African American</a> manager."
        },
        {
            "year": 1987,
            "html": "<a href=\"https://wikipedia.org/wiki/Los_Angeles_Dodgers\" title=\"Los Angeles Dodgers\">Los Angeles Dodgers</a> executive <a href=\"https://wikipedia.org/wiki/Al_Campanis\" title=\"Al Campanis\">Al Campanis</a> resigns amid controversy over <a href=\"https://wikipedia.org/wiki/Racism\" title=\"Racism\">racist</a> remarks he had made while on <i><a href=\"https://wikipedia.org/wiki/Nightline\" title=\"Nightline\">Nightline</a></i>."
        },
        {
            "year": 1992,
            "html": "Retired <a href=\"https://wikipedia.org/wiki/Tennis\" title=\"Tennis\">tennis</a> great <a href=\"https://wikipedia.org/wiki/Arthur_Ashe\" title=\"Arthur Ashe\">Arthur Ashe</a> announces that he has <a href=\"https://wikipedia.org/wiki/AIDS\" title=\"AIDS\">AIDS</a>, acquired from <a href=\"https://wikipedia.org/wiki/Blood_transfusion\" title=\"Blood transfusion\">blood transfusions</a> during one of his two heart surgeries."
        },
        {
            "year": 1993,
            "html": "The <a href=\"https://wikipedia.org/wiki/Republic_of_North_Macedonia\" title=\"Republic of North Macedonia\">Republic of North Macedonia</a> joins the <a href=\"https://wikipedia.org/wiki/United_Nations\" title=\"United Nations\">United Nations</a>."
        },
        {
            "year": 1993,
            "html": "The <a href=\"https://wikipedia.org/wiki/Space_Shuttle_Discovery\" title=\"Space Shuttle Discovery\">Space Shuttle <i>Discovery</i></a> is launched on mission <a href=\"https://wikipedia.org/wiki/STS-56\" title=\"STS-56\">STS-56</a>."
        },
        {
            "year": 2004,
            "html": "<a href=\"https://wikipedia.org/wiki/War_in_Darfur\" title=\"War in Darfur\">War in Darfur</a>: The <a href=\"https://wikipedia.org/wiki/April_8_Humanitarian_Ceasefire_Agreement\" title=\"April 8 Humanitarian Ceasefire Agreement\">Humanitarian Ceasefire Agreement</a> is signed by the <a href=\"https://wikipedia.org/wiki/Sudan\" title=\"Sudan\">Sudanese</a> government, the <a href=\"https://wikipedia.org/wiki/Justice_and_Equality_Movement\" title=\"Justice and Equality Movement\">Justice and Equality Movement</a>, and the <a href=\"https://wikipedia.org/wiki/Sudan_Liberation_Movement/Army\" title=\"Sudan Liberation Movement/Army\">Sudan Liberation Movement/Army</a>."
        },
        {
            "year": 2005,
            "html": "A <a href=\"https://wikipedia.org/wiki/Solar_eclipse_of_April_8,_2005\" title=\"Solar eclipse of April 8, 2005\">solar eclipse</a> occurs, visible over areas of the <a href=\"https://wikipedia.org/wiki/Pacific_Ocean\" title=\"Pacific Ocean\">Pacific Ocean</a> and Latin American countries such as <a href=\"https://wikipedia.org/wiki/Costa_Rica\" title=\"Costa Rica\">Costa Rica</a>, <a href=\"https://wikipedia.org/wiki/Panama\" title=\"Panama\">Panama</a>, <a href=\"https://wikipedia.org/wiki/Colombia\" title=\"Colombia\">Colombia</a> and <a href=\"https://wikipedia.org/wiki/Venezuela\" title=\"Venezuela\">Venezuela</a>."
        },
        {
            "year": 2006,
            "html": "<a href=\"https://wikipedia.org/wiki/Shedden_massacre\" title=\"Shedden massacre\">Shedden massacre</a>: The bodies of eight men, all shot to death, are found in a field in <a href=\"https://wikipedia.org/wiki/Shedden,_Elgin_County,_Ontario\" title=\"Shedden, Elgin County, Ontario\">Shedden, Elgin County, Ontario</a>. The murders are soon linked to the <a href=\"https://wikipedia.org/wiki/Bandidos_Motorcycle_Club\" title=\"Bandidos Motorcycle Club\">Bandidos Motorcycle Club</a>."
        },
        {
            "year": 2008,
            "html": "The construction of the <a href=\"https://wikipedia.org/wiki/Bahrain_World_Trade_Center\" title=\"Bahrain World Trade Center\">world's first skyscraper to integrate wind turbines</a> is completed in <a href=\"https://wikipedia.org/wiki/Bahrain\" title=\"Bahrain\">Bahrain</a>."
        },
        {
            "year": 2010,
            "html": "U.S. President <a href=\"https://wikipedia.org/wiki/Barack_Obama\" title=\"Barack Obama\">Barack Obama</a> and Russian President <a href=\"https://wikipedia.org/wiki/Dmitry_Medvedev\" title=\"Dmitry Medvedev\">Dmitry Medvedev</a> sign the <a href=\"https://wikipedia.org/wiki/New_START\" title=\"New START\">New START Treaty</a>."
        },
        {
            "year": 2013,
            "html": "The <a href=\"https://wikipedia.org/wiki/Islamic_State_of_Iraq\" title=\"Islamic State of Iraq\">Islamic State of Iraq</a> enters the <a href=\"https://wikipedia.org/wiki/Syrian_Civil_War\" title=\"Syrian Civil War\">Syrian Civil War</a> and begins by declaring a merger with the <a href=\"https://wikipedia.org/wiki/Al-Nusra_Front\" title=\"Al-Nusra Front\">Al-Nusra Front</a> under the name <a href=\"https://wikipedia.org/wiki/Islamic_State_of_Iraq_and_the_Levant\" title=\"Islamic State of Iraq and the Levant\">Islamic State of Iraq and ash-Sham</a>."
        },
        {
            "year": 2014,
            "html": "<a href=\"https://wikipedia.org/wiki/Windows_XP\" title=\"Windows XP\">Windows XP</a> reaches its standard <a href=\"https://wikipedia.org/wiki/End-of-life_product\" title=\"End-of-life product\">End Of Life</a> and is no longer supported."
        },
        {
            "year": 2020,
            "html": "<a href=\"https://wikipedia.org/wiki/Bernie_Sanders\" title=\"Bernie Sanders\">Bernie Sanders</a> ends his <a href=\"https://wikipedia.org/wiki/Bernie_Sanders_2020_presidential_campaign\" title=\"Bernie Sanders 2020 presidential campaign\">presidential campaign</a>, leaving <a href=\"https://wikipedia.org/wiki/Joe_Biden\" title=\"Joe Biden\">Joe Biden</a> as the <a href=\"https://wikipedia.org/wiki/Democratic_Party_(United_States)\" title=\"Democratic Party (United States)\">Democratic Party</a>'s nominee."
        }
    ],
    "births": [
        {
            "year": 1320,
            "html": "<a href=\"https://wikipedia.org/wiki/Peter_I_of_Portugal\" title=\"Peter I of Portugal\">Peter I of Portugal</a> (d. 1367)"
        },
        {
            "year": 1408,
            "html": "<a href=\"https://wikipedia.org/wiki/Jadwiga_of_Lithuania\" title=\"Jadwiga of Lithuania\">Jadwiga of Lithuania</a>, Polish princess (d. 1431)"
        },
        {
            "year": 1435,
            "html": "<a href=\"https://wikipedia.org/wiki/John_Clifford,_9th_Baron_de_Clifford\" title=\"John Clifford, 9th Baron de Clifford\">John Clifford, 9th Baron de Clifford</a>, English noble (d. 1461)"
        },
        {
            "year": 1533,
            "html": "<a href=\"https://wikipedia.org/wiki/Claudio_Merulo\" title=\"Claudio Merulo\">Claudio Merulo</a>, Italian organist and composer (d. 1604)"
        },
        {
            "year": 1536,
            "html": "<a href=\"https://wikipedia.org/wiki/Barbara_of_Hesse\" title=\"Barbara of Hesse\">Barbara of Hesse</a> (d. 1597)"
        },
        {
            "year": 1541,
            "html": "<a href=\"https://wikipedia.org/wiki/Michele_Mercati\" title=\"Michele Mercati\">Michele Mercati</a>, Italian physician and archaeologist (d. 1593)"
        },
        {
            "year": 1580,
            "html": "<a href=\"https://wikipedia.org/wiki/William_Herbert,_3rd_Earl_of_Pembroke\" title=\"William Herbert, 3rd Earl of Pembroke\">William Herbert, 3rd Earl of Pembroke</a>, English noble, courtier and patron of the arts (d. 1630)"
        },
        {
            "year": 1596,
            "html": "<a href=\"https://wikipedia.org/wiki/Juan_van_der_Hamen\" title=\"Juan van der Hamen\">Juan van der Hamen</a>, Spanish artist (d. 1631)"
        },
        {
            "year": 1605,
            "html": "<a href=\"https://wikipedia.org/wiki/Philip_IV_of_Spain\" title=\"Philip IV of Spain\">Philip IV of Spain</a> (d. 1665)"
        },
        {
            "year": 1605,
            "html": "<a href=\"https://wikipedia.org/wiki/Mary_Stuart_(1605%E2%80%931607)\" title=\"Mary Stuart (1605-1607)\">Mary Stuart</a>, English-Scottish princess (d. 1607)"
        },
        {
            "year": 1641,
            "html": "<a href=\"https://wikipedia.org/wiki/Henry_Sydney,_1st_Earl_of_Romney\" title=\"Henry Sydney, 1st Earl of Romney\">Henry Sydney, 1st Earl of Romney</a>, English general and politician, <a href=\"https://wikipedia.org/wiki/Secretary_of_State_for_the_Northern_Department\" title=\"Secretary of State for the Northern Department\">Secretary of State for the Northern Department</a> (d. 1704)"
        },
        {
            "year": 1692,
            "html": "<a href=\"https://wikipedia.org/wiki/Giuseppe_Tartini\" title=\"Giuseppe Tartini\">Giuseppe Tartini</a>, Italian violinist and composer (d. 1770)"
        },
        {
            "year": 1726,
            "html": "<a href=\"https://wikipedia.org/wiki/Lewis_Morris\" title=\"Lewis Morris\">Lewis Morris</a>, American judge and politician (d. 1798)"
        },
        {
            "year": 1732,
            "html": "<a href=\"https://wikipedia.org/wiki/David_Rittenhouse\" title=\"David Rittenhouse\">David Rittenhouse</a>, American astronomer and mathematician (d. 1796)"
        },
        {
            "year": 1761,
            "html": "<a href=\"https://wikipedia.org/wiki/William_Joseph_Chaminade\" title=\"William Joseph Chaminade\">William Joseph Chaminade</a>, French priest, founded the <a href=\"https://wikipedia.org/wiki/Society_of_Mary_(Marianists)\" title=\"Society of Mary (Marianists)\">Society of Mary</a> (d. 1850)"
        },
        {
            "year": 1770,
            "html": "<a href=\"https://wikipedia.org/wiki/John_Thomas_Campbell\" title=\"John Thomas Campbell\">John Thomas Campbell</a>, Irish-Australian banker and politician (d. 1830)"
        },
        {
            "year": 1798,
            "html": "<a href=\"https://wikipedia.org/wiki/Dionysios_Solomos\" title=\"Dionysios Solomos\">Dionysios Solomos</a>, Greek poet and author (d. 1857)"
        },
        {
            "year": 1818,
            "html": "<a href=\"https://wikipedia.org/wiki/Christian_IX_of_Denmark\" title=\"Christian IX of Denmark\">Christian IX of Denmark</a> (d. 1906)"
        },
        {
            "year": 1818,
            "html": "<a href=\"https://wikipedia.org/wiki/August_Wilhelm_von_Hofmann\" title=\"August Wilhelm von Hofmann\">August Wilhelm von Hofmann</a>, German chemist and academic (d. 1892)"
        },
        {
            "year": 1826,
            "html": "<a href=\"https://wikipedia.org/wiki/Pancha_Carrasco\" title=\"Pancha Carrasco\">Pancha Carrasco</a>, Costa Rican soldier (d. 1890)"
        },
        {
            "year": 1827,
            "html": "<a href=\"https://wikipedia.org/wiki/Ram%C3%B3n_Emeterio_Betances\" title=\"Ramón Emeterio Betances\">Ramón Emeterio Betances</a>, Puerto Rican ophthalmologist, journalist, and politician (d. 1898)"
        },
        {
            "year": 1842,
            "html": "<a href=\"https://wikipedia.org/wiki/Elizabeth_Bacon_Custer\" title=\"Elizabeth Bacon Custer\">Elizabeth Bacon Custer</a>, American author and educator (d. 1933)"
        },
        {
            "year": 1859,
            "html": "<a href=\"https://wikipedia.org/wiki/Edmund_Husserl\" title=\"Edmund Husserl\">Edmund Husserl</a>, German Jewish-Austrian mathematician and philosopher (d. 1938)"
        },
        {
            "year": 1864,
            "html": "<a href=\"https://wikipedia.org/wiki/Carlos_Deltour\" title=\"Carlos Deltour\">Carlos Deltour</a>, French rower and rugby player (d. 1920)"
        },
        {
            "year": 1867,
            "html": "<a href=\"https://wikipedia.org/wiki/Allen_Butler_Talcott\" title=\"Allen Butler Talcott\">Allen Butler Talcott</a>, American painter and educator (d. 1908)"
        },
        {
            "year": 1869,
            "html": "<a href=\"https://wikipedia.org/wiki/Harvey_Cushing\" title=\"Harvey Cushing\">Harvey Cushing</a>, American surgeon and academic (d. 1939)"
        },
        {
            "year": 1871,
            "html": "<a href=\"https://wikipedia.org/wiki/Clarence_Hudson_White\" title=\"Clarence Hudson White\">Clarence Hudson White</a>, American photographer and educator (d. 1925)"
        },
        {
            "year": 1874,
            "html": "<a href=\"https://wikipedia.org/wiki/Manuel_D%C3%ADaz_(fencer)\" title=\"Manuel Díaz (fencer)\">Manuel Díaz</a>, Cuban fencer (d. 1929)"
        },
        {
            "year": 1874,
            "html": "<a href=\"https://wikipedia.org/wiki/Stanis%C5%82aw_Taczak\" title=\"Stanisław Taczak\">Stanisław Taczak</a>, Polish general (d. 1960)"
        },
        {
            "year": 1875,
            "html": "<a href=\"https://wikipedia.org/wiki/Albert_I_of_Belgium\" title=\"Albert I of Belgium\">Albert I of Belgium</a> (d. 1934)"
        },
        {
            "year": 1883,
            "html": "<a href=\"https://wikipedia.org/wiki/R._P._Keigwin\" title=\"R. P. Keigwin\">R. P. Keigwin</a>, English cricketer and academic (d. 1972)"
        },
        {
            "year": 1883,
            "html": "<a href=\"https://wikipedia.org/wiki/Julius_Seljamaa\" title=\"Julius Seljamaa\">Julius Seljamaa</a>, Estonian journalist and politician, <a href=\"https://wikipedia.org/wiki/Minister_of_Foreign_Affairs_of_Estonia\" title=\"Minister of Foreign Affairs of Estonia\">Minister of Foreign Affairs of Estonia</a> (d. 1936)"
        },
        {
            "year": 1885,
            "html": "<a href=\"https://wikipedia.org/wiki/Dimitrios_Levidis\" title=\"Dimitrios Levidis\">Dimitrios Levidis</a>, Greek-French soldier, composer, and educator (d. 1951)"
        },
        {
            "year": 1886,
            "html": "<a href=\"https://wikipedia.org/wiki/Margaret_Ayer_Barnes\" title=\"Margaret Ayer Barnes\">Margaret Ayer Barnes</a>, American author and playwright (d. 1967)"
        },
        {
            "year": 1888,
            "html": "<a href=\"https://wikipedia.org/wiki/Dennis_Ch%C3%A1vez\" title=\"Dennis Chávez\">Dennis Chávez</a>, American journalist and politician (d. 1962)"
        },
        {
            "year": 1889,
            "html": "<a href=\"https://wikipedia.org/wiki/Adrian_Boult\" title=\"Adrian Boult\">Adrian Boult</a>, English conductor (d. 1983)"
        },
        {
            "year": 1892,
            "html": "<a href=\"https://wikipedia.org/wiki/Richard_Neutra\" title=\"Richard Neutra\">Richard Neutra</a>, Austrian-American architect, designer of the <a href=\"https://wikipedia.org/wiki/Los_Angeles_County_Hall_of_Records\" title=\"Los Angeles County Hall of Records\">Los Angeles County Hall of Records</a> (d. 1970)"
        },
        {
            "year": 1892,
            "html": "<a href=\"https://wikipedia.org/wiki/Mary_Pickford\" title=\"Mary Pickford\">Mary Pickford</a>, Canadian-American actress, producer, screenwriter and co-founder of <a href=\"https://wikipedia.org/wiki/United_Artists\" title=\"United Artists\">United Artists</a> (d. 1979)"
        },
        {
            "year": 1896,
            "html": "<a href=\"https://wikipedia.org/wiki/Yip_Harburg\" title=\"Yip Harburg\">Yip Harburg</a>, American composer (d. 1981)"
        },
        {
            "year": 1900,
            "html": "<a href=\"https://wikipedia.org/wiki/Marie_Byles\" title=\"Marie Byles\">Marie Byles</a>, Australian solicitor (d. 1979) "
        },
        {
            "year": 1902,
            "html": "<a href=\"https://wikipedia.org/wiki/Andrew_Irvine_(mountaineer)\" title=\"Andrew Irvine (mountaineer)\">Andrew Irvine</a>, English mountaineer and explorer (d. 1924)"
        },
        {
            "year": 1902,
            "html": "<a href=\"https://wikipedia.org/wiki/Maria_Maksakova_Sr.\" title=\"Maria Maksakova Sr.\">Maria Maksakova Sr.</a>, Russian soprano (d. 1974)"
        },
        {
            "year": 1904,
            "html": "<a href=\"https://wikipedia.org/wiki/John_Hicks\" title=\"John Hicks\">John Hicks</a>, English economist and academic, <a href=\"https://wikipedia.org/wiki/Nobel_Memorial_Prize_in_Economic_Sciences\" title=\"Nobel Memorial Prize in Economic Sciences\">Nobel Prize</a> laureate (d. 1989)"
        },
        {
            "year": 1904,
            "html": "<a href=\"https://wikipedia.org/wiki/Hirsch_Jacobs\" title=\"Hirsch Jacobs\">Hirsch Jacobs</a>, American horse trainer (d. 1970)"
        },
        {
            "year": 1905,
            "html": "<a href=\"https://wikipedia.org/wiki/Joachim_B%C3%BCchner\" title=\"Joachim Büchner\">Joachim Büchner</a>, German sprinter and graphic designer (d. 1978)"
        },
        {
            "year": 1905,
            "html": "<a href=\"https://wikipedia.org/wiki/Helen_Joseph\" title=\"Helen Joseph\">Helen Joseph</a>, English-South African activist (d. 1992)"
        },
        {
            "year": 1905,
            "html": "<a href=\"https://wikipedia.org/wiki/Erwin_Keller\" title=\"Erwin Keller\">Erwin Keller</a>, German field hockey player (d. 1971)"
        },
        {
            "year": 1906,
            "html": "<a href=\"https://wikipedia.org/wiki/Raoul_Jobin\" title=\"Raoul Jobin\">Raoul Jobin</a>, Canadian tenor and educator (d. 1974)"
        },
        {
            "year": 1908,
            "html": "<a href=\"https://wikipedia.org/wiki/Hugo_Fregonese\" title=\"Hugo Fregonese\">Hugo Fregonese</a>, Argentinian director and screenwriter (d. 1987)"
        },
        {
            "year": 1909,
            "html": "<a href=\"https://wikipedia.org/wiki/John_Fante\" title=\"John Fante\">John Fante</a>, American author and screenwriter (d. 1983)"
        },
        {
            "year": 1910,
            "html": "<a href=\"https://wikipedia.org/wiki/George_Musso\" title=\"George Musso\">George Musso</a>, American football player and police officer (d. 2000)"
        },
        {
            "year": 1911,
            "html": "<a href=\"https://wikipedia.org/wiki/Melvin_Calvin\" title=\"Melvin Calvin\">Melvin Calvin</a>, American chemist and academic, <a href=\"https://wikipedia.org/wiki/Nobel_Prize_in_Chemistry\" title=\"Nobel Prize in Chemistry\">Nobel Prize</a> laureate (d. 1997)"
        },
        {
            "year": 1911,
            "html": "<a href=\"https://wikipedia.org/wiki/Emil_Cioran\" title=\"Emil Cioran\">Emil Cioran</a>, Romanian-French philosopher and academic (d. 1995)"
        },
        {
            "year": 1912,
            "html": "<a href=\"https://wikipedia.org/wiki/Alois_Brunner\" title=\"Alois Brunner\">Alois Brunner</a>, Austrian-German <a href=\"https://wikipedia.org/wiki/SS\" title=\"SS\">SS</a> officer (d. 2001 or 2010)"
        },
        {
            "year": 1912,
            "html": "<a href=\"https://wikipedia.org/wiki/Sonja_Henie\" title=\"Sonja Henie\">Sonja Henie</a>, Norwegian-American figure skater and actress (d. 1969)"
        },
        {
            "year": 1914,
            "html": "<a href=\"https://wikipedia.org/wiki/Mar%C3%ADa_F%C3%A9lix\" title=\"María Félix\">María Félix</a>, <a href=\"https://wikipedia.org/wiki/Yaqui\" title=\"Yaqui\">Yaqui</a>/<a href=\"https://wikipedia.org/wiki/Basques\" title=\"Basques\">Basque</a>-Mexican actress (d. 2002)"
        },
        {
            "year": 1915,
            "html": "<a href=\"https://wikipedia.org/wiki/Ivan_Supek\" title=\"Ivan Supek\">Ivan Supek</a>, Croatian physicist, philosopher and writer (d. 2007)"
        },
        {
            "year": 1917,
            "html": "<a href=\"https://wikipedia.org/wiki/Winifred_Asprey\" title=\"Winifred Asprey\">Winifred Asprey</a>, American mathematician and computer scientist (d. 2007)"
        },
        {
            "year": 1917,
            "html": "<a href=\"https://wikipedia.org/wiki/Lloyd_Bott\" title=\"Lloyd Bott\">Lloyd Bott</a>, Australian public servant (d. 2004)"
        },
        {
            "year": 1917,
            "html": "<a href=\"https://wikipedia.org/wiki/Hubertus_Ernst\" title=\"Hubertus Ernst\">Hubertus Ernst</a>, Dutch bishop (d. 2017)"
        },
        {
            "year": 1917,
            "html": "<a href=\"https://wikipedia.org/wiki/Grigori_Kuzmin\" title=\"Grigori Kuzmin\">Grigori Kuzmin</a>, Russian-Estonian astronomer (d. 1988)"
        },
        {
            "year": 1918,
            "html": "<a href=\"https://wikipedia.org/wiki/Betty_Ford\" title=\"Betty Ford\">Betty Ford</a>, American wife of <a href=\"https://wikipedia.org/wiki/Gerald_Ford\" title=\"Gerald Ford\">Gerald Ford</a>, 40th <a href=\"https://wikipedia.org/wiki/First_Lady_of_the_United_States\" title=\"First Lady of the United States\">First Lady of the United States</a> (d. 2011)"
        },
        {
            "year": 1918,
            "html": "<a href=\"https://wikipedia.org/wiki/Glendon_Swarthout\" title=\"Glendon Swarthout\">Glendon Swarthout</a>, American author and academic (d. 1992)"
        },
        {
            "year": 1919,
            "html": "<a href=\"https://wikipedia.org/wiki/Ian_Smith\" title=\"Ian Smith\">Ian Smith</a>, Zimbabwean lieutenant and politician, 1st <a href=\"https://wikipedia.org/wiki/Prime_Minister_of_Rhodesia\" title=\"Prime Minister of Rhodesia\">Prime Minister of Rhodesia</a> (d. 2007)"
        },
        {
            "year": 1921,
            "html": "<a href=\"https://wikipedia.org/wiki/Franco_Corelli\" title=\"Franco Corelli\">Franco Corelli</a>, Italian tenor and actor (d. 2003)"
        },
        {
            "year": 1920,
            "html": "<a href=\"https://wikipedia.org/wiki/Carmen_McRae\" title=\"Carmen McRae\">Carmen McRae</a>, American singer-songwriter, pianist, and actress (d. 1994)"
        },
        {
            "year": 1921,
            "html": "<a href=\"https://wikipedia.org/wiki/Jan_Nov%C3%A1k_(composer)\" title=\"Jan Novák (composer)\">Jan Novák</a>, Czech composer (d. 1984)"
        },
        {
            "year": 1921,
            "html": "<a href=\"https://wikipedia.org/wiki/Herman_van_Raalte\" title=\"Herman van Raalte\">Herman van Raalte</a>, Dutch footballer (d. 2013)"
        },
        {
            "year": 1923,
            "html": "<a href=\"https://wikipedia.org/wiki/George_Fisher_(cartoonist)\" title=\"George Fisher (cartoonist)\">George Fisher</a>, American cartoonist (d. 2003)"
        },
        {
            "year": 1923,
            "html": "<a href=\"https://wikipedia.org/wiki/Edward_Mulhare\" title=\"Edward Mulhare\">Edward Mulhare</a>, Irish-American actor (d. 1997)"
        },
        {
            "year": 1924,
            "html": "<a href=\"https://wikipedia.org/wiki/Fr%C3%A9d%C3%A9ric_Back\" title=\"Frédéric Back\">Frédéric Back</a>, German-Canadian animator, director, and screenwriter (d. 2013)"
        },
        {
            "year": 1924,
            "html": "<a href=\"https://wikipedia.org/wiki/Anthony_Farrar-Hockley\" title=\"Anthony Farrar-Hockley\">Anthony Farrar-Hockley</a>, English general and historian (d. 2006)"
        },
        {
            "year": 1924,
            "html": "<a href=\"https://wikipedia.org/wiki/Kumar_Gandharva\" title=\"Kumar Gandharva\">Kumar Gandharva</a>, Hindustani classical singer (d. 1992)"
        },
        {
            "year": 1924,
            "html": "<a href=\"https://wikipedia.org/wiki/Sara_Northrup_Hollister\" title=\"Sara Northrup Hollister\">Sara Northrup Hollister</a>, American occultist (d. 1997)"
        },
        {
            "year": 1926,
            "html": "<a href=\"https://wikipedia.org/wiki/Henry_N._Cobb\" title=\"Henry N. Cobb\">Henry N. Cobb</a>, American architect and academic, co-founded <a href=\"https://wikipedia.org/wiki/Pei_Cobb_Freed_%26_Partners\" title=\"Pei Cobb Freed &amp; Partners\">Pei Cobb Freed &amp; Partners</a> (d. 2020)"
        },
        {
            "year": 1926,
            "html": "<a href=\"https://wikipedia.org/wiki/Shecky_Greene\" title=\"Shecky Greene\">Shecky Greene</a>, American comedian (d. 2023)"
        },
        {
            "year": 1926,
            "html": "<a href=\"https://wikipedia.org/wiki/J%C3%BCrgen_Moltmann\" title=\"Jürgen Moltmann\">Jürgen Moltmann</a>, German theologian and academic"
        },
        {
            "year": 1927,
            "html": "<a href=\"https://wikipedia.org/wiki/Tilly_Armstrong\" title=\"Tilly Armstrong\">Tilly Armstrong</a>, English author (d. 2010)"
        },
        {
            "year": 1927,
            "html": "<a href=\"https://wikipedia.org/wiki/Ollie_Mitchell\" title=\"Ollie Mitchell\">Ollie Mitchell</a>, American trumpet player and bandleader (d. 2013)"
        },
        {
            "year": 1928,
            "html": "<a href=\"https://wikipedia.org/wiki/Fred_Ebb\" title=\"Fred Ebb\">Fred Ebb</a>, American lyricist (d. 2004)"
        },
        {
            "year": 1929,
            "html": "<a href=\"https://wikipedia.org/wiki/Jacques_Brel\" title=\"Jacques Brel\">Jacques Brel</a>, Belgian singer-songwriter and actor (d. 1978)"
        },
        {
            "year": 1929,
            "html": "<a href=\"https://wikipedia.org/wiki/Renzo_De_Felice\" title=\"Renzo De Felice\">Renzo De Felice</a>, Italian historian and author (d. 1996)"
        },
        {
            "year": 1930,
            "html": "<a href=\"https://wikipedia.org/wiki/Carlos_Hugo,_Duke_of_Parma\" title=\"Carlos Hugo, Duke of Parma\">Carlos Hugo, Duke of Parma</a> (d. 2010)"
        },
        {
            "year": 1931,
            "html": "<a href=\"https://wikipedia.org/wiki/John_Gavin\" title=\"John Gavin\">John Gavin</a>, American actor and diplomat, <a href=\"https://wikipedia.org/wiki/United_States_Ambassador_to_Mexico\" title=\"United States Ambassador to Mexico\">United States Ambassador to Mexico</a> (d. 2018)"
        },
        {
            "year": 1932,
            "html": "<a href=\"https://wikipedia.org/wiki/Iskandar_of_Johor\" title=\"Iskandar of Johor\">Iskandar of Johor</a> (d. 2010)"
        },
        {
            "year": 1933,
            "html": "<a href=\"https://wikipedia.org/wiki/James_Lockhart_(historian)\" title=\"James Lockhart (historian)\">James Lockhart</a>, American scholar of colonial Latin America, especially <a href=\"https://wikipedia.org/wiki/Nahua_people\" title=\"Nahua people\">Nahua peoples</a> (d. 2014)"
        },
        {
            "year": 1934,
            "html": "<a href=\"https://wikipedia.org/wiki/Kisho_Kurokawa\" title=\"Kisho Kurokawa\">Kisho Kurokawa</a>, Japanese architect, designed the <a href=\"https://wikipedia.org/wiki/Nakagin_Capsule_Tower\" title=\"Nakagin Capsule Tower\">Nakagin Capsule Tower</a> and <a href=\"https://wikipedia.org/wiki/Singapore_Flyer\" title=\"Singapore Flyer\">Singapore Flyer</a> (d. 2007)"
        },
        {
            "year": 1935,
            "html": "<a href=\"https://wikipedia.org/wiki/Oscar_Zeta_Acosta\" title=\"Oscar Zeta Acosta\">Oscar Zeta Acosta</a>, American lawyer and politician (d. 1974)"
        },
        {
            "year": 1935,
            "html": "<a href=\"https://wikipedia.org/wiki/Albert_Bustamante\" title=\"Albert Bustamante\">Albert Bustamante</a>, American soldier, educator, and politician"
        },
        {
            "year": 1937,
            "html": "<a href=\"https://wikipedia.org/wiki/Tony_Barton_(footballer)\" title=\"Tony Barton (footballer)\">Tony Barton</a>, English footballer and manager (d. 1993)"
        },
        {
            "year": 1937,
            "html": "<a href=\"https://wikipedia.org/wiki/Seymour_Hersh\" title=\"Seymour Hersh\">Seymour Hersh</a>, American journalist and author"
        },
        {
            "year": 1937,
            "html": "<a href=\"https://wikipedia.org/wiki/Momo_Kapor\" title=\"Momo Kapor\">Momo Kapor</a>, Serbian author and painter (d. 2010)"
        },
        {
            "year": 1938,
            "html": "<a href=\"https://wikipedia.org/wiki/Kofi_Annan\" title=\"Kofi Annan\">Kofi Annan</a>, Ghanaian economist and diplomat, 7th <a href=\"https://wikipedia.org/wiki/Secretary-General_of_the_United_Nations\" title=\"Secretary-General of the United Nations\">Secretary-General of the United Nations</a> (d. 2018)"
        },
        {
            "year": 1938,
            "html": "<a href=\"https://wikipedia.org/wiki/John_Hamm\" title=\"John Hamm\">John Hamm</a>, Canadian physician and politician, 25th <a href=\"https://wikipedia.org/wiki/Premier_of_Nova_Scotia\" title=\"Premier of Nova Scotia\">Premier of Nova Scotia</a>"
        },
        {
            "year": 1938,
            "html": "<a href=\"https://wikipedia.org/wiki/Mary_W._Gray\" title=\"Mary W. Gray\">Mary W. Gray</a>, American mathematician, statistician, and lawyer"
        },
        {
            "year": 1939,
            "html": "<a href=\"https://wikipedia.org/wiki/Manolis_Angelopoulos\" title=\"Manolis Angelopoulos\">Manolis Angelopoulos</a>, Greek singer, composer and songwriter (d. 1989)"
        },
        {
            "year": 1939,
            "html": "<a href=\"https://wikipedia.org/wiki/John_Arbuthnott_(microbiologist)\" title=\"John Arbuthnott (microbiologist)\">John Arbuthnott</a>, Scottish microbiologist and academic"
        },
        {
            "year": 1939,
            "html": "<a href=\"https://wikipedia.org/wiki/Trina_Schart_Hyman\" title=\"Trina Schart Hyman\">Trina Schart Hyman</a>, American author and illustrator (d. 2004)"
        },
        {
            "year": 1939,
            "html": "<a href=\"https://wikipedia.org/wiki/Martin_J._Schreiber\" title=\"Martin J. Schreiber\">Martin J. Schreiber</a>, American politician, 39th <a href=\"https://wikipedia.org/wiki/Governor_of_Wisconsin\" title=\"Governor of Wisconsin\">Governor of Wisconsin</a>"
        },
        {
            "year": 1940,
            "html": "<a href=\"https://wikipedia.org/wiki/John_Havlicek\" title=\"John Havlicek\">John Havlicek</a>, American basketball player (d. 2019)"
        },
        {
            "year": 1941,
            "html": "<a href=\"https://wikipedia.org/wiki/Vivienne_Westwood\" title=\"Vivienne Westwood\">Vivienne Westwood</a>, English fashion designer (d. 2022)"
        },
        {
            "year": 1942,
            "html": "<a href=\"https://wikipedia.org/wiki/Tony_Banks,_Baron_Stratford\" title=\"Tony Banks, Baron Stratford\">Tony Banks, Baron Stratford</a>, Northern Irish politician, <a href=\"https://wikipedia.org/wiki/Minister_for_Sport_and_the_Olympics\" title=\"Minister for Sport and the Olympics\">Minister for Sport and the Olympics</a> (d. 2006)"
        },
        {
            "year": 1942,
            "html": "<a href=\"https://wikipedia.org/wiki/Roger_Chapman\" title=\"Roger Chapman\">Roger Chapman</a>, English singer-songwriter and guitarist"
        },
        {
            "year": 1942,
            "html": "<a href=\"https://wikipedia.org/wiki/Douglas_Trumbull\" title=\"Douglas Trumbull\">Douglas Trumbull</a>, American director, producer, and special effects artist (d. 2022)"
        },
        {
            "year": 1943,
            "html": "<a href=\"https://wikipedia.org/wiki/Michael_Bennett_(theater)\" title=\"Michael Bennett (theater)\">Michael Bennett</a>, American dancer, choreographer, and director (d. 1987)"
        },
        {
            "year": 1943,
            "html": "<a href=\"https://wikipedia.org/wiki/Miller_Farr\" title=\"Miller Farr\">Miller Farr</a>, American football player"
        },
        {
            "year": 1943,
            "html": "<a href=\"https://wikipedia.org/wiki/James_Herbert\" title=\"James Herbert\">James Herbert</a>, English author and illustrator (d. 2013)"
        },
        {
            "year": 1943,
            "html": "<a href=\"https://wikipedia.org/wiki/Chris_Orr_(artist)\" title=\"Chris Orr (artist)\">Chris Orr</a>, English painter and illustrator"
        },
        {
            "year": 1944,
            "html": "<a href=\"https://wikipedia.org/wiki/Hywel_Bennett\" title=\"Hywel Bennett\">Hywel Bennett</a>, Welsh actor (d. 2017)"
        },
        {
            "year": 1944,
            "html": "<a href=\"https://wikipedia.org/wiki/Odd_Nerdrum\" title=\"Odd Nerdrum\">Odd Nerdrum</a>, Swedish-Norwegian painter and illustrator"
        },
        {
            "year": 1945,
            "html": "<a href=\"https://wikipedia.org/wiki/Derrick_Walker\" title=\"Derrick Walker\">Derrick Walker</a>, Scottish businessman"
        },
        {
            "year": 1945,
            "html": "<a href=\"https://wikipedia.org/wiki/Jang_Yong\" title=\"Jang Yong\">Jang Yong</a>, South Korean actor"
        },
        {
            "year": 1946,
            "html": "<a href=\"https://wikipedia.org/wiki/Catfish_Hunter\" title=\"Catfish Hunter\">Catfish Hunter</a>, American baseball player (d. 1999)"
        },
        {
            "year": 1946,
            "html": "<a href=\"https://wikipedia.org/wiki/Tim_Thomerson\" title=\"Tim Thomerson\">Tim Thomerson</a>, American actor and producer"
        },
        {
            "year": 1947,
            "html": "<a href=\"https://wikipedia.org/wiki/Tom_DeLay\" title=\"Tom DeLay\">Tom DeLay</a>, American lawyer and politician"
        },
        {
            "year": 1947,
            "html": "<a href=\"https://wikipedia.org/wiki/Steve_Howe_(musician)\" title=\"Steve Howe (musician)\">Steve Howe</a>, English guitarist, songwriter, and producer"
        },
        {
            "year": 1947,
            "html": "<a href=\"https://wikipedia.org/wiki/Pascal_Lamy\" title=\"Pascal Lamy\">Pascal Lamy</a>, French businessman and politician, <a href=\"https://wikipedia.org/wiki/European_Commissioner_for_Trade\" title=\"European Commissioner for Trade\">European Commissioner for Trade</a>"
        },
        {
            "year": 1947,
            "html": "<a href=\"https://wikipedia.org/wiki/Larry_Norman\" title=\"Larry Norman\">Larry Norman</a>, American singer-songwriter, and producer (d. 2008)"
        },
        {
            "year": 1948,
            "html": "<a href=\"https://wikipedia.org/wiki/Barbara_Young,_Baroness_Young_of_Old_Scone\" title=\"Barbara Young, Baroness Young of Old Scone\">Barbara Young, Baroness Young of Old Scone</a>, Scottish academic and politician"
        },
        {
            "year": 1949,
            "html": "<a href=\"https://wikipedia.org/wiki/K._C._Kamalasabayson\" title=\"K. C. Kamalasabayson\">K. C. Kamalasabayson</a>, Sri Lankan lawyer and politician, 39th <a href=\"https://wikipedia.org/wiki/Attorney_General_of_Sri_Lanka\" title=\"Attorney General of Sri Lanka\">Attorney General of Sri Lanka</a> (d. 2007)"
        },
        {
            "year": 1949,
            "html": "<a href=\"https://wikipedia.org/wiki/John_Madden_(director)\" title=\"John Madden (director)\">John Madden</a>, English director and producer"
        },
        {
            "year": 1949,
            "html": "<a href=\"https://wikipedia.org/wiki/Brenda_Russell\" title=\"Brenda Russell\">Brenda Russell</a>, African-American-Canadian singer-songwriter and keyboard player"
        },
        {
            "year": 1949,
            "html": "<a href=\"https://wikipedia.org/wiki/John_Scott_(sociologist)\" title=\"John Scott (sociologist)\">John Scott</a>, English sociologist and academic"
        },
        {
            "year": 1950,
            "html": "<a href=\"https://wikipedia.org/wiki/Grzegorz_Lato\" title=\"Grzegorz Lato\">Grzegorz Lato</a>, Polish footballer and coach"
        },
        {
            "year": 1951,
            "html": "<a href=\"https://wikipedia.org/wiki/Gerd_Andres\" title=\"Gerd Andres\">Gerd Andres</a>, German politician"
        },
        {
            "year": 1951,
            "html": "<a href=\"https://wikipedia.org/wiki/Geir_Haarde\" title=\"Geir Haarde\">Geir Haarde</a>, Icelandic economist, journalist, and politician, 23rd <a href=\"https://wikipedia.org/wiki/Prime_Minister_of_Iceland\" title=\"Prime Minister of Iceland\">Prime Minister of Iceland</a>"
        },
        {
            "year": 1951,
            "html": "<a href=\"https://wikipedia.org/wiki/Mel_Schacher\" title=\"Mel Schacher\">Mel Schacher</a>, American bass player"
        },
        {
            "year": 1951,
            "html": "<a href=\"https://wikipedia.org/wiki/Joan_Sebastian\" title=\"Joan Sebastian\">Joan Sebastian</a>, Mexican singer-songwriter and actor (d. 2015)"
        },
        {
            "year": 1951,
            "html": "<a href=\"https://wikipedia.org/wiki/Phil_Schaap\" title=\"Phil Schaap\">Phil Schaap</a>, American jazz disc jockey and historian (d. 2021)"
        },
        {
            "year": 1952,
            "html": "<a href=\"https://wikipedia.org/wiki/Ahmet_Piri%C5%9Ftina\" title=\"Ahmet Piriştina\">Ahmet Piriştina</a>, Turkish politician (d. 2004)"
        },
        {
            "year": 1954,
            "html": "<a href=\"https://wikipedia.org/wiki/Gary_Carter\" title=\"Gary Carter\">Gary Carter</a>, American baseball player and coach (d. 2012)"
        },
        {
            "year": 1954,
            "html": "<a href=\"https://wikipedia.org/wiki/Princess_Lalla_Amina_of_Morocco\" title=\"Princess Lalla Amina of Morocco\">Princess Lalla Amina of Morocco</a> (d. 2012)"
        },
        {
            "year": 1954,
            "html": "<a href=\"https://wikipedia.org/wiki/G.V._Loganathan\" title=\"G.V. Loganathan\">G.V. Loganathan</a>, Indian-American engineer and academic (d. 2007)"
        },
        {
            "year": 1955,
            "html": "<a href=\"https://wikipedia.org/wiki/Gerrie_Coetzee\" title=\"Gerrie Coetzee\">Gerrie Coetzee</a>, South African boxer (d. 2023)"
        },
        {
            "year": 1955,
            "html": "<a href=\"https://wikipedia.org/wiki/Ron_Johnson\" title=\"Ron Johnson\">Ron Johnson</a>, American businessman and politician"
        },
        {
            "year": 1955,
            "html": "<a href=\"https://wikipedia.org/wiki/Barbara_Kingsolver\" title=\"Barbara Kingsolver\">Barbara Kingsolver</a>, American novelist, essayist and poet"
        },
        {
            "year": 1955,
            "html": "<a href=\"https://wikipedia.org/wiki/David_Wu\" title=\"David Wu\">David Wu</a>, Taiwanese-American lawyer and politician"
        },
        {
            "year": 1956,
            "html": "<a href=\"https://wikipedia.org/wiki/Michael_Benton\" title=\"Michael Benton\">Michael Benton</a>, Scottish-English paleontologist and academic"
        },
        {
            "year": 1956,
            "html": "<a href=\"https://wikipedia.org/wiki/Christine_Boisson\" title=\"Christine Boisson\">Christine Boisson</a>, French actress"
        },
        {
            "year": 1956,
            "html": "<a href=\"https://wikipedia.org/wiki/Roman_Dragoun\" title=\"Roman Dragoun\">Roman Dragoun</a>, Czech singer-songwriter and keyboard player"
        },
        {
            "year": 1958,
            "html": "<a href=\"https://wikipedia.org/wiki/Detlef_Bruckhoff\" title=\"Detlef Bruckhoff\">Detlef Bruckhoff</a>, German footballer"
        },
        {
            "year": 1958,
            "html": "<a href=\"https://wikipedia.org/wiki/Tom_Petranoff\" title=\"Tom Petranoff\">Tom Petranoff</a>, American javelin thrower and coach"
        },
        {
            "year": 1959,
            "html": "<a href=\"https://wikipedia.org/wiki/Alain_Bondue\" title=\"Alain Bondue\">Alain Bondue</a>, French cyclist"
        },
        {
            "year": 1960,
            "html": "<a href=\"https://wikipedia.org/wiki/John_Schneider_(screen_actor)\" title=\"John Schneider (screen actor)\">John Schneider</a>, American actor and country singer"
        },
        {
            "year": 1961,
            "html": "<a href=\"https://wikipedia.org/wiki/Richard_Hatch_(Survivor_contestant)\" title=\"Richard Hatch (Survivor contestant)\">Richard Hatch</a>, American reality contestant"
        },
        {
            "year": 1961,
            "html": "<a href=\"https://wikipedia.org/wiki/Brian_McDermott_(footballer)\" title=\"Brian McDermott (footballer)\">Brian McDermott</a>, English footballer and manager"
        },
        {
            "year": 1962,
            "html": "<a href=\"https://wikipedia.org/wiki/Paddy_Lowe\" title=\"Paddy Lowe\">Paddy Lowe</a>, English engineer"
        },
        {
            "year": 1962,
            "html": "<a href=\"https://wikipedia.org/wiki/Izzy_Stradlin\" title=\"Izzy Stradlin\">Izzy Stradlin</a>, American guitarist and songwriter"
        },
        {
            "year": 1963,
            "html": "<a href=\"https://wikipedia.org/wiki/Tine_Asmundsen\" title=\"Tine Asmundsen\">Tine Asmundsen</a>, Norwegian bassist"
        },
        {
            "year": 1963,
            "html": "<a href=\"https://wikipedia.org/wiki/Julian_Lennon\" title=\"Julian Lennon\">Julian Lennon</a>, English singer-songwriter"
        },
        {
            "year": 1963,
            "html": "<a href=\"https://wikipedia.org/wiki/Dean_Norris\" title=\"Dean Norris\">Dean Norris</a>, American actor"
        },
        {
            "year": 1963,
            "html": "<a href=\"https://wikipedia.org/wiki/Terry_Porter\" title=\"Terry Porter\">Terry Porter</a>, American basketball player and coach"
        },
        {
            "year": 1963,
            "html": "<a href=\"https://wikipedia.org/wiki/Donita_Sparks\" title=\"Donita Sparks\">Donita Sparks</a>, American singer-songwriter and guitarist"
        },
        {
            "year": 1963,
            "html": "<a href=\"https://wikipedia.org/wiki/Alec_Stewart\" title=\"Alec Stewart\">Alec Stewart</a>, English cricketer"
        },
        {
            "year": 1963,
            "html": "<a href=\"https://wikipedia.org/wiki/Seth_Tobias\" title=\"Seth Tobias\">Seth Tobias</a>, American businessman (d. 2007)"
        },
        {
            "year": 1964,
            "html": "<a href=\"https://wikipedia.org/wiki/Biz_Markie\" title=\"Biz Markie\">Biz Markie</a>, American rapper, producer, and actor (d. 2021)"
        },
        {
            "year": 1964,
            "html": "<a href=\"https://wikipedia.org/wiki/John_McGinlay\" title=\"John McGinlay\">John McGinlay</a>, Scottish footballer and manager"
        },
        {
            "year": 1965,
            "html": "<a href=\"https://wikipedia.org/wiki/Steven_Blaney\" title=\"Steven Blaney\">Steven Blaney</a>, Canadian businessman and politician, 5th <a href=\"https://wikipedia.org/wiki/Minister_of_Public_Safety\" title=\"Minister of Public Safety\">Canadian Minister of Public Safety</a>"
        },
        {
            "year": 1965,
            "html": "<a href=\"https://wikipedia.org/wiki/Michael_Jones_(rugby_union)\" title=\"Michael Jones (rugby union)\">Michael Jones</a>, New Zealand rugby player and coach"
        },
        {
            "year": 1966,
            "html": "<a href=\"https://wikipedia.org/wiki/Iveta_Barto%C5%A1ov%C3%A1\" title=\"Iveta Bartošová\">Iveta Bartošová</a>, Czech singer and actress (d. 2014)"
        },
        {
            "year": 1966,
            "html": "<a href=\"https://wikipedia.org/wiki/Mark_Blundell\" title=\"Mark Blundell\">Mark Blundell</a>, English race car driver"
        },
        {
            "year": 1966,
            "html": "<a href=\"https://wikipedia.org/wiki/Andy_Currier\" title=\"Andy Currier\">Andy Currier</a>, English rugby league player"
        },
        {
            "year": 1966,
            "html": "<a href=\"https://wikipedia.org/wiki/Charlotte_Dawson\" title=\"Charlotte Dawson\">Charlotte Dawson</a>, New Zealand-Australian television host (d. 2014)"
        },
        {
            "year": 1966,
            "html": "<a href=\"https://wikipedia.org/wiki/Dalton_Grant\" title=\"Dalton Grant\">Dalton Grant</a>, English high jumper"
        },
        {
            "year": 1966,
            "html": "<a href=\"https://wikipedia.org/wiki/Mazinho\" title=\"Mazinho\">Mazinho</a>, Brazilian footballer, coach, and manager"
        },
        {
            "year": 1966,
            "html": "<a href=\"https://wikipedia.org/wiki/Harri_Rovanper%C3%A4\" title=\"Harri Rovanperä\">Harri Rovanperä</a>, Finnish race car driver"
        },
        {
            "year": 1966,
            "html": "<a href=\"https://wikipedia.org/wiki/Evripidis_Stylianidis\" title=\"Evripidis Stylianidis\">Evripidis Stylianidis</a>, Greek lawyer and politician, <a href=\"https://wikipedia.org/wiki/Ministry_of_the_Interior_and_Administrative_Reconstruction\" title=\"Ministry of the Interior and Administrative Reconstruction\">Greek Minister for the Interior</a>"
        },
        {
            "year": 1966,
            "html": "<a href=\"https://wikipedia.org/wiki/Robin_Wright\" title=\"Robin Wright\">Robin Wright</a>, American actress, director, producer"
        },
        {
            "year": 1967,
            "html": "<a href=\"https://wikipedia.org/wiki/Kenny_Benjamin\" title=\"Kenny Benjamin\">Kenny Benjamin</a>, Antiguan cricketer"
        },
        {
            "year": 1968,
            "html": "<a href=\"https://wikipedia.org/wiki/Patricia_Arquette\" title=\"Patricia Arquette\">Patricia Arquette</a>, American actress and director"
        },
        {
            "year": 1968,
            "html": "<a href=\"https://wikipedia.org/wiki/Patricia_Girard\" title=\"Patricia Girard\">Patricia Girard</a>, French runner and hurdler"
        },
        {
            "year": 1968,
            "html": "<a href=\"https://wikipedia.org/wiki/Tracy_Grammer\" title=\"Tracy Grammer\">Tracy Grammer</a>, American singer-songwriter and guitarist"
        },
        {
            "year": 1971,
            "html": "<a href=\"https://wikipedia.org/wiki/Darren_Jessee\" title=\"Darren Jessee\">Darren Jessee</a>, American singer-songwriter and drummer"
        },
        {
            "year": 1972,
            "html": "<a href=\"https://wikipedia.org/wiki/Paul_Gray_(American_musician)\" title=\"Paul Gray (American musician)\">Paul Gray</a>, American bass player and songwriter (d. 2010)"
        },
        {
            "year": 1972,
            "html": "<a href=\"https://wikipedia.org/wiki/Sergei_Magnitsky\" title=\"Sergei Magnitsky\">Sergei Magnitsky</a>, Russian lawyer and accountant (d. 2009)"
        },
        {
            "year": 1973,
            "html": "<a href=\"https://wikipedia.org/wiki/Khaled_Badra\" title=\"Khaled Badra\">Khaled Badra</a>, Tunisian footballer"
        },
        {
            "year": 1973,
            "html": "<a href=\"https://wikipedia.org/wiki/Emma_Caulfield\" title=\"Emma Caulfield\">Emma Caulfield</a>, American actress"
        },
        {
            "year": 1974,
            "html": "<a href=\"https://wikipedia.org/wiki/Toutai_Kefu\" title=\"Toutai Kefu\">Toutai Kefu</a>, Tongan-Australian rugby player"
        },
        {
            "year": 1974,
            "html": "<a href=\"https://wikipedia.org/wiki/Chris_Kyle\" title=\"Chris Kyle\">Chris Kyle</a>, American sniper and memoirist (d. 2013)"
        },
        {
            "year": 1974,
            "html": "<a href=\"https://wikipedia.org/wiki/Nnedi_Okorafor\" title=\"Nnedi Okorafor\">Nnedi Okorafor</a>, Nigerian-American author and educator"
        },
        {
            "year": 1975,
            "html": "<a href=\"https://wikipedia.org/wiki/Anouk_(singer)\" title=\"Anouk (singer)\">Anouk</a>, Dutch singer"
        },
        {
            "year": 1975,
            "html": "<a href=\"https://wikipedia.org/wiki/Francesco_Flachi\" title=\"Francesco Flachi\">Francesco Flachi</a>, Italian footballer"
        },
        {
            "year": 1975,
            "html": "<a href=\"https://wikipedia.org/wiki/Timo_P%C3%A9rez\" title=\"Timo Pérez\">Timo Pérez</a>, Dominican-American baseball player"
        },
        {
            "year": 1975,
            "html": "<a href=\"https://wikipedia.org/wiki/Funda_Arar\" title=\"Funda Arar\">Funda Arar</a>, Turkish singer"
        },
        {
            "year": 1977,
            "html": "<a href=\"https://wikipedia.org/wiki/Ana_de_la_Reguera\" title=\"Ana de la Reguera\">Ana de la Reguera</a>, Mexican actress"
        },
        {
            "year": 1977,
            "html": "<a href=\"https://wikipedia.org/wiki/Mehran_Ghassemi\" title=\"Mehran Ghassemi\">Mehran Ghassemi</a>, Iranian journalist and author (d. 2008)"
        },
        {
            "year": 1977,
            "html": "<a href=\"https://wikipedia.org/wiki/Mark_Spencer_(computer_engineer)\" title=\"Mark Spencer (computer engineer)\">Mark Spencer</a>, American computer programmer and engineer"
        },
        {
            "year": 1978,
            "html": "<a href=\"https://wikipedia.org/wiki/Daigo_(musician)\" title=\"Daigo (musician)\">Daigo</a>, Japanese singer-songwriter, actor, and voice actor"
        },
        {
            "year": 1978,
            "html": "<a href=\"https://wikipedia.org/wiki/Bernt_Haas\" title=\"Bernt Haas\">Bernt Haas</a>, Austrian-Swiss footballer"
        },
        {
            "year": 1978,
            "html": "<a href=\"https://wikipedia.org/wiki/Rachel_Roberts_(model)\" title=\"Rachel Roberts (model)\">Rachel Roberts</a>, Canadian model and actress"
        },
        {
            "year": 1978,
            "html": "<a href=\"https://wikipedia.org/wiki/Jocelyn_Robichaud\" title=\"Jocelyn Robichaud\">Jocelyn Robichaud</a>, Canadian tennis player and coach"
        },
        {
            "year": 1978,
            "html": "<a href=\"https://wikipedia.org/wiki/Evans_Rutto\" title=\"Evans Rutto\">Evans Rutto</a>, Kenyan runner"
        },
        {
            "year": 1979,
            "html": "<a href=\"https://wikipedia.org/wiki/Alexi_Laiho\" title=\"Alexi Laiho\">Alexi Laiho</a>, Finnish singer-songwriter and guitarist (d. 2020)"
        },
        {
            "year": 1979,
            "html": "<a href=\"https://wikipedia.org/wiki/Amit_Trivedi\" title=\"Amit Trivedi\">Amit Trivedi</a>, Indian singer-songwriter"
        },
        {
            "year": 1980,
            "html": "<a href=\"https://wikipedia.org/wiki/Manuel_Ortega_(singer)\" title=\"Manuel Ortega (singer)\">Manuel Ortega</a>, Austrian singer"
        },
        {
            "year": 1980,
            "html": "<a href=\"https://wikipedia.org/wiki/Katee_Sackhoff\" title=\"Katee Sackhoff\">Katee Sackhoff</a>, American actress"
        },
        {
            "year": 1980,
            "html": "<a href=\"https://wikipedia.org/wiki/Mariko_Seyama\" title=\"Mariko Seyama\">Mariko Seyama</a>, Japanese announcer, photographer, and model"
        },
        {
            "year": 1981,
            "html": "<a href=\"https://wikipedia.org/wiki/Fr%C3%A9d%C3%A9rick_Bousquet\" title=\"Frédérick Bousquet\">Frédérick Bousquet</a>, French swimmer"
        },
        {
            "year": 1981,
            "html": "<a href=\"https://wikipedia.org/wiki/Taylor_Kitsch\" title=\"Taylor Kitsch\">Taylor Kitsch</a>, Canadian actor and model"
        },
        {
            "year": 1981,
            "html": "<a href=\"https://wikipedia.org/wiki/Ofer_Shechter\" title=\"Ofer Shechter\">Ofer Shechter</a>, Israeli model, actor, and screenwriter"
        },
        {
            "year": 1982,
            "html": "<a href=\"https://wikipedia.org/wiki/Gennady_Golovkin\" title=\"Gennady Golovkin\">Gennady Golovkin</a>, Kazakhstani boxer"
        },
        {
            "year": 1982,
            "html": "<a href=\"https://wikipedia.org/wiki/Brett_White\" title=\"Brett White\">Brett White</a>, Australian rugby league player"
        },
        {
            "year": 1982,
            "html": "<a href=\"https://wikipedia.org/wiki/Allu_Arjun\" title=\"Allu Arjun\">Allu Arjun</a>, Indian actor"
        },
        {
            "year": 1983,
            "html": "<a href=\"https://wikipedia.org/wiki/Tatyana_Petrova_Arkhipova\" title=\"Tatyana Petrova Arkhipova\">Tatyana Petrova Arkhipova</a>, Russian runner"
        },
        {
            "year": 1984,
            "html": "<a href=\"https://wikipedia.org/wiki/Michelle_Donelan\" title=\"Michelle Donelan\">Michelle Donelan</a>, British politician"
        },
        {
            "year": 1984,
            "html": "<a href=\"https://wikipedia.org/wiki/Ezra_Koenig\" title=\"Ezra Koenig\">Ezra Koenig</a>, American singer-songwriter and guitarist"
        },
        {
            "year": 1984,
            "html": "<a href=\"https://wikipedia.org/wiki/Pablo_Portillo\" title=\"Pablo Portillo\">Pablo Portillo</a>, Mexican singer and actor"
        },
        {
            "year": 1984,
            "html": "<a href=\"https://wikipedia.org/wiki/Taran_Noah_Smith\" title=\"Taran Noah Smith\">Taran Noah Smith</a>, American actor"
        },
        {
            "year": 1985,
            "html": "<a href=\"https://wikipedia.org/wiki/Patrick_Schliwa\" title=\"Patrick Schliwa\">Patrick Schliwa</a>, German rugby player"
        },
        {
            "year": 1985,
            "html": "<a href=\"https://wikipedia.org/wiki/Yemane_Tsegay\" title=\"Yemane Tsegay\">Yemane Tsegay</a>, Ethiopian runner"
        },
        {
            "year": 1986,
            "html": "<a href=\"https://wikipedia.org/wiki/Igor_Akinfeev\" title=\"Igor Akinfeev\">Igor Akinfeev</a>, Russian footballer"
        },
        {
            "year": 1986,
            "html": "<a href=\"https://wikipedia.org/wiki/F%C3%A9lix_Hern%C3%A1ndez\" title=\"Félix Hernández\">Félix Hernández</a>, Venezuelan baseball player"
        },
        {
            "year": 1986,
            "html": "<a href=\"https://wikipedia.org/wiki/Carlos_Santana_(baseball)\" title=\"Carlos Santana (baseball)\">Carlos Santana</a>, Dominican baseball player"
        },
        {
            "year": 1987,
            "html": "<a href=\"https://wikipedia.org/wiki/Royston_Drenthe\" title=\"Royston Drenthe\">Royston Drenthe</a>, Dutch footballer"
        },
        {
            "year": 1987,
            "html": "<a href=\"https://wikipedia.org/wiki/Jeremy_Hellickson\" title=\"Jeremy Hellickson\">Jeremy Hellickson</a>, American baseball player"
        },
        {
            "year": 1987,
            "html": "<a href=\"https://wikipedia.org/wiki/Elton_John_(footballer)\" title=\"Elton John (footballer)\">Elton John</a>, Trinidadian footballer"
        },
        {
            "year": 1987,
            "html": "<a href=\"https://wikipedia.org/wiki/Sam_Rapira\" title=\"Sam Rapira\">Sam Rapira</a>, New Zealand rugby league player"
        },
        {
            "year": 1988,
            "html": "<a href=\"https://wikipedia.org/wiki/Jenni_Asserholt\" title=\"Jenni Asserholt\">Jenni Asserholt</a>, Swedish ice hockey player"
        },
        {
            "year": 1990,
            "html": "<a href=\"https://wikipedia.org/wiki/Kim_Jong-hyun_(singer)\" title=\"Kim Jong-hyun (singer)\">Kim Jong-hyun</a>, South Korean singer (d. 2017) "
        },
        {
            "year": 1992,
            "html": "<a href=\"https://wikipedia.org/wiki/Jeff_McNeil\" title=\"Jeff McNeil\">Jeff McNeil</a>, American baseball player"
        },
        {
            "year": 1993,
            "html": "<a href=\"https://wikipedia.org/wiki/Viktor_Arvidsson\" title=\"Viktor Arvidsson\">Viktor Arvidsson</a>, Swedish ice hockey player"
        },
        {
            "year": 1994,
            "html": "<a href=\"https://wikipedia.org/wiki/Josh_Chudleigh\" title=\"Josh Chudleigh\">Josh Chudleigh</a>, Australian rugby league player"
        },
        {
            "year": 1995,
            "html": "<a href=\"https://wikipedia.org/wiki/Cedi_Osman\" title=\"Cedi Osman\">Cedi Osman</a>, Turkish professional basketball player"
        },
        {
            "year": 1996,
            "html": "<a href=\"https://wikipedia.org/wiki/Anna_Korakaki\" title=\"Anna Korakaki\">Anna Korakaki</a>, Greek Olympic shooter"
        },
        {
            "year": 1997,
            "html": "<a href=\"https://wikipedia.org/wiki/Kim_Woo-jin\" title=\"Kim Woo-jin\">Kim Woo-jin</a>, South Korean singer"
        },
        {
            "year": 1997,
            "html": "<a href=\"https://wikipedia.org/wiki/Saygrace\" title=\"Saygrace\">Saygrace</a>, Australian singer and songwriter"
        },
        {
            "year": 1997,
            "html": "<a href=\"https://wikipedia.org/wiki/Roquan_Smith\" title=\"Roquan Smith\">Roquan Smith</a>, American football player"
        },
        {
            "year": 1997,
            "html": "<a href=\"https://wikipedia.org/wiki/Arno_Verschueren\" title=\"Arno Verschueren\">Arno Verschueren</a>, Belgian footballer"
        },
        {
            "year": 1998,
            "html": "<a href=\"https://wikipedia.org/wiki/Lavinia_Valbonesi\" title=\"Lavinia Valbonesi\">Lavinia Valbonesi</a>, Ecuadorian nutritionist, businesswoman and <a href=\"https://wikipedia.org/wiki/First_Lady_of_Ecuador\" title=\"First Lady of Ecuador\">First Lady-designate of Ecuador</a>"
        },
        {
            "year": 1999,
            "html": "<a href=\"https://wikipedia.org/wiki/CeeDee_Lamb\" title=\"CeeDee Lamb\">CeeDee Lamb</a>, American football player"
        },
        {
            "year": 2002,
            "html": "<a href=\"https://wikipedia.org/wiki/Vikt%C3%B3ria_Forster\" title=\"Viktória Forster\">Viktória Forster</a>, Slovak track and field athlete"
        },
        {
            "year": 2002,
            "html": "<a href=\"https://wikipedia.org/wiki/Skai_Jackson\" title=\"Skai Jackson\">Skai Jackson</a>, American actress"
        }
    ],
    "deaths": [
        {
            "year": 217,
            "html": "<a href=\"https://wikipedia.org/wiki/Caracalla\" title=\"Caracalla\">Caracalla</a>, Roman emperor (b. 188)"
        },
        {
            "year": 622,
            "html": "<a href=\"https://wikipedia.org/wiki/Prince_Sh%C5%8Dtoku\" title=\"Prince Shōtoku\">Shōtoku</a>, Japanese prince (b. 572)"
        },
        {
            "year": 632,
            "html": "<a href=\"https://wikipedia.org/wiki/Charibert_II\" title=\"Charibert II\">Charibert II</a>, Frankish king (b. 607)"
        },
        {
            "year": 894,
            "html": "<a href=\"https://wikipedia.org/wiki/Adalelm,_Count_of_Troyes\" title=\"Adalelm, Count of Troyes\">Adalelm</a>, Frankish nobleman"
        },
        {
            "year": 944,
            "html": "<a href=\"https://wikipedia.org/wiki/Wang_Yanxi\" title=\"Wang Yanxi\">Wang Yanxi</a>, Chinese emperor"
        },
        {
            "year": 956,
            "html": "<a href=\"https://wikipedia.org/wiki/Gilbert,_Duke_of_Burgundy\" title=\"Gilbert, Duke of Burgundy\">Gilbert</a>, Frankish nobleman"
        },
        {
            "year": 967,
            "html": "<a href=\"https://wikipedia.org/wiki/Mu%27izz_al-Dawla\" title=\"Mu'izz al-Dawla\">Mu'izz al-Dawla</a>, Buyid emir (b. 915)"
        },
        {
            "year": 1143,
            "html": "<a href=\"https://wikipedia.org/wiki/John_II_Komnenos\" title=\"John II Komnenos\">John II Komnenos</a>, Byzantine emperor (b. 1087)"
        },
        {
            "year": 1150,
            "html": "<a href=\"https://wikipedia.org/wiki/Gertrude_of_Babenberg,_Duchess_of_Bohemia\" title=\"Gertrude of Babenberg, Duchess of Bohemia\">Gertrude of Babenberg</a>, duchess of Bohemia (b. 1118)"
        },
        {
            "year": 1321,
            "html": "<a href=\"https://wikipedia.org/wiki/Thomas_of_Tolentino\" title=\"Thomas of Tolentino\">Thomas of Tolentino</a>, Italian-Franciscan missionary (b. c. 1255)"
        },
        {
            "year": 1338,
            "html": "<a href=\"https://wikipedia.org/wiki/Stephen_Gravesend\" title=\"Stephen Gravesend\">Stephen Gravesend</a>, bishop of London"
        },
        {
            "year": 1364,
            "html": "<a href=\"https://wikipedia.org/wiki/John_II_of_France\" title=\"John II of France\">John II</a>, French king (b. 1319)"
        },
        {
            "year": 1450,
            "html": "<a href=\"https://wikipedia.org/wiki/Sejong_the_Great\" title=\"Sejong the Great\">Sejong the Great</a>, Korean king (b. 1397)"
        },
        {
            "year": 1461,
            "html": "<a href=\"https://wikipedia.org/wiki/Georg_von_Peuerbach\" title=\"Georg von Peuerbach\">Georg von Peuerbach</a>, German mathematician and astronomer (b. 1423)"
        },
        {
            "year": 1492,
            "html": "<a href=\"https://wikipedia.org/wiki/Lorenzo_de%27_Medici\" title=\"Lorenzo de' Medici\">Lorenzo de' Medici</a>, Italian ruler (b. 1449)"
        },
        {
            "year": 1551,
            "html": "<a href=\"https://wikipedia.org/wiki/Oda_Nobuhide\" title=\"Oda Nobuhide\">Oda Nobuhide</a>, Japanese warlord (b. 1510)"
        },
        {
            "year": 1586,
            "html": "<a href=\"https://wikipedia.org/wiki/Martin_Chemnitz\" title=\"Martin Chemnitz\">Martin Chemnitz</a>, Lutheran theologian and reformer (b. 1522)"
        },
        {
            "year": 1608,
            "html": "<a href=\"https://wikipedia.org/wiki/Magdalen_Dacre\" title=\"Magdalen Dacre\">Magdalen Dacre</a>, English noble (b. 1538)"
        },
        {
            "year": 1612,
            "html": "<a href=\"https://wikipedia.org/wiki/Anne_Catherine_of_Brandenburg\" title=\"Anne Catherine of Brandenburg\">Anne Catherine of Brandenburg</a> (b. 1575)"
        },
        {
            "year": 1691,
            "html": "<a href=\"https://wikipedia.org/wiki/Carlo_Rainaldi\" title=\"Carlo Rainaldi\">Carlo Rainaldi</a>, Italian architect, designed the <a href=\"https://wikipedia.org/wiki/Santa_Maria_dei_Miracoli_and_Santa_Maria_in_Montesanto\" title=\"Santa Maria dei Miracoli and Santa Maria in Montesanto\">Santa Maria dei Miracoli and Santa Maria in Montesanto</a> (b. 1611)"
        },
        {
            "year": 1697,
            "html": "<a href=\"https://wikipedia.org/wiki/Niels_Juel\" title=\"Niels Juel\">Niels Juel</a>, Norwegian-Danish admiral (b. 1629)"
        },
        {
            "year": 1704,
            "html": "<a href=\"https://wikipedia.org/wiki/Hiob_Ludolf\" title=\"Hiob Ludolf\">Hiob Ludolf</a>, German orientalist and philologist (b. 1624)"
        },
        {
            "year": 1704,
            "html": "<a href=\"https://wikipedia.org/wiki/Henry_Sydney,_1st_Earl_of_Romney\" title=\"Henry Sydney, 1st Earl of Romney\">Henry Sydney, 1st Earl of Romney</a>, English colonel and politician, <a href=\"https://wikipedia.org/wiki/Lord_Lieutenant_of_Ireland\" title=\"Lord Lieutenant of Ireland\">Lord Lieutenant of Ireland</a> (b. 1641)"
        },
        {
            "year": 1709,
            "html": "<a href=\"https://wikipedia.org/wiki/Wolfgang_Dietrich_of_Castell-Remlingen\" title=\"Wolfgang Dietrich of Castell-Remlingen\">Wolfgang Dietrich of Castell-Remlingen</a>, German nobleman (b. 1641)"
        },
        {
            "year": 1725,
            "html": "<a href=\"https://wikipedia.org/wiki/John_Wise_(clergyman)\" title=\"John Wise (clergyman)\">John Wise</a>, American minister (b. 1652)"
        },
        {
            "year": 1735,
            "html": "<a href=\"https://wikipedia.org/wiki/Francis_II_R%C3%A1k%C3%B3czi\" title=\"Francis II Rákóczi\">Francis II Rákóczi</a>, Hungarian prince (b. 1676)"
        },
        {
            "year": 1848,
            "html": "<a href=\"https://wikipedia.org/wiki/Gaetano_Donizetti\" title=\"Gaetano Donizetti\">Gaetano Donizetti</a>, Italian composer (b. 1797)"
        },
        {
            "year": 1860,
            "html": "<a href=\"https://wikipedia.org/wiki/Istv%C3%A1n_Sz%C3%A9chenyi\" title=\"István Széchenyi\">István Széchenyi</a>, Hungarian statesman and reformer (b.1791) "
        },
        {
            "year": 1861,
            "html": "<a href=\"https://wikipedia.org/wiki/Elisha_Otis\" title=\"Elisha Otis\">Elisha Otis</a>, American businessman, founded the <a href=\"https://wikipedia.org/wiki/Otis_Elevator_Company\" title=\"Otis Elevator Company\">Otis Elevator Company</a> (b. 1811)"
        },
        {
            "year": 1870,
            "html": "<a href=\"https://wikipedia.org/wiki/Charles_Auguste_de_B%C3%A9riot\" title=\"Charles Auguste de Bériot\">Charles Auguste de Bériot</a>, Belgian violinist and composer (b. 1802)"
        },
        {
            "year": 1877,
            "html": "<a href=\"https://wikipedia.org/wiki/Bernardino_Ant%C3%B3nio_Gomes_Jr.\" title=\"Bernardino António Gomes Jr.\">Bernardino António Gomes</a>, Portuguese physician and naturalist (b. 1806)"
        },
        {
            "year": 1894,
            "html": "<a href=\"https://wikipedia.org/wiki/Bankim_Chandra_Chattopadhyay\" title=\"Bankim Chandra Chattopadhyay\">Bankim Chandra Chattopadhyay</a>, Indian journalist, author, and poet (b. 1838)"
        },
        {
            "year": 1906,
            "html": "<a href=\"https://wikipedia.org/wiki/Auguste_Deter\" title=\"Auguste Deter\">Auguste Deter</a>, German woman, first person diagnosed with <a href=\"https://wikipedia.org/wiki/Alzheimer%27s_disease\" title=\"Alzheimer's disease\">Alzheimer's disease</a> (b. 1850)"
        },
        {
            "year": 1919,
            "html": "<a href=\"https://wikipedia.org/wiki/Lor%C3%A1nd_E%C3%B6tv%C3%B6s\" title=\"Loránd Eötvös\">Loránd Eötvös</a>, Hungarian physicist, academic, and politician, <a href=\"https://wikipedia.org/wiki/Minister_of_Education_(Hungary)\" title=\"Minister of Education (Hungary)\">Hungarian Minister of Education</a> (b. 1848)"
        },
        {
            "year": 1920,
            "html": "<a href=\"https://wikipedia.org/wiki/Charles_Griffes\" title=\"Charles Griffes\">Charles Griffes</a>, American pianist and composer (b. 1884)"
        },
        {
            "year": 1931,
            "html": "<a href=\"https://wikipedia.org/wiki/Erik_Axel_Karlfeldt\" title=\"Erik Axel Karlfeldt\">Erik Axel Karlfeldt</a>, Swedish poet <a href=\"https://wikipedia.org/wiki/Nobel_Prize_in_Literature\" title=\"Nobel Prize in Literature\">Nobel Prize</a> laureate (b. 1864)"
        },
        {
            "year": 1936,
            "html": "<a href=\"https://wikipedia.org/wiki/R%C3%B3bert_B%C3%A1r%C3%A1ny\" title=\"Róbert Bárány\">Róbert Bárány</a>, Austrian physician and academic, <a href=\"https://wikipedia.org/wiki/Nobel_Prize_in_Physiology_or_Medicine\" title=\"Nobel Prize in Physiology or Medicine\">Nobel Prize</a> laureate (b. 1876)"
        },
        {
            "year": 1936,
            "html": "<a href=\"https://wikipedia.org/wiki/Bo%C5%BEena_Bene%C5%A1ov%C3%A1\" title=\"Božena Benešová\">Božena Benešová</a>, Czech poet and novelist (b. 1873)"
        },
        {
            "year": 1941,
            "html": "<a href=\"https://wikipedia.org/wiki/Marcel_Pr%C3%A9vost\" title=\"Marcel Prévost\">Marcel Prévost</a>, French novelist and playwright (b. 1862)"
        },
        {
            "year": 1942,
            "html": "<a href=\"https://wikipedia.org/wiki/Kostas_Skarvelis\" title=\"Kostas Skarvelis\">Kostas Skarvelis</a>, Greek guitarist and composer (b. 1880)"
        },
        {
            "year": 1947,
            "html": "<a href=\"https://wikipedia.org/wiki/Olaf_Frydenlund\" title=\"Olaf Frydenlund\">Olaf Frydenlund</a>, Norwegian target shooter (b. 1862)"
        },
        {
            "year": 1950,
            "html": "<a href=\"https://wikipedia.org/wiki/Vaslav_Nijinsky\" title=\"Vaslav Nijinsky\">Vaslav Nijinsky</a>, Polish dancer and choreographer (b. 1890)"
        },
        {
            "year": 1959,
            "html": "<a href=\"https://wikipedia.org/wiki/Marios_Makrionitis\" title=\"Marios Makrionitis\">Marios Makrionitis</a>, Roman Catholic Archbishop of Athens (b. 1913)"
        },
        {
            "year": 1961,
            "html": "<a href=\"https://wikipedia.org/wiki/Joseph_Carrodus\" title=\"Joseph Carrodus\">Joseph Carrodus</a>, Australian public servant (b. 1885)"
        },
        {
            "year": 1962,
            "html": "<a href=\"https://wikipedia.org/wiki/Juan_Belmonte\" title=\"Juan Belmonte\">Juan Belmonte</a>, Spanish bullfighter (b. 1892)"
        },
        {
            "year": 1965,
            "html": "<a href=\"https://wikipedia.org/wiki/Lars_Hanson\" title=\"Lars Hanson\">Lars Hanson</a>, Swedish actor (b. 1886)"
        },
        {
            "year": 1969,
            "html": "<a href=\"https://wikipedia.org/wiki/Zinaida_Aksentyeva\" title=\"Zinaida Aksentyeva\">Zinaida Aksentyeva</a>, Ukrainian astronomer (b. 1900)"
        },
        {
            "year": 1973,
            "html": "<a href=\"https://wikipedia.org/wiki/Pablo_Picasso\" title=\"Pablo Picasso\">Pablo Picasso</a>, Spanish painter and sculptor (b. 1881)"
        },
        {
            "year": 1974,
            "html": "<a href=\"https://wikipedia.org/wiki/James_Charles_McGuigan\" title=\"James Charles McGuigan\">James Charles McGuigan</a>, Canadian cardinal (b. 1894)"
        },
        {
            "year": 1979,
            "html": "<a href=\"https://wikipedia.org/wiki/Breece_D%27J_Pancake\" title=\"Breece D'J Pancake\">Breece D'J Pancake</a>, American short story writer (b. 1952)"
        },
        {
            "year": 1981,
            "html": "<a href=\"https://wikipedia.org/wiki/Omar_Bradley\" title=\"Omar Bradley\">Omar Bradley</a>, American general (b. 1893)"
        },
        {
            "year": 1983,
            "html": "<a href=\"https://wikipedia.org/wiki/Isamu_Kosugi\" title=\"Isamu Kosugi\">Isamu Kosugi</a>, Japanese actor and director (b. 1904)"
        },
        {
            "year": 1984,
            "html": "<a href=\"https://wikipedia.org/wiki/Pyotr_Kapitsa\" title=\"Pyotr Kapitsa\">Pyotr Kapitsa</a>, Russian physicist and academic, <a href=\"https://wikipedia.org/wiki/Nobel_Prize_in_Physics\" title=\"Nobel Prize in Physics\">Nobel Prize</a> laureate (b. 1894)"
        },
        {
            "year": 1985,
            "html": "<a href=\"https://wikipedia.org/wiki/John_Frederick_Coots\" title=\"John Frederick Coots\">John Frederick Coots</a>, American pianist and composer (b. 1897)"
        },
        {
            "year": 1990,
            "html": "<a href=\"https://wikipedia.org/wiki/Ryan_White\" title=\"Ryan White\">Ryan White</a>, American activist, inspired the <a href=\"https://wikipedia.org/wiki/Ryan_White_Care_Act\" title=\"Ryan White Care Act\">Ryan White Care Act</a> (b. 1971)"
        },
        {
            "year": 1991,
            "html": "<a href=\"https://wikipedia.org/wiki/Dead_(musician)\" title=\"Dead (musician)\">Per Ohlin</a>, Swedish musician (b. 1969)"
        },
        {
            "year": 1992,
            "html": "<a href=\"https://wikipedia.org/wiki/Daniel_Bovet\" title=\"Daniel Bovet\">Daniel Bovet</a>, Swiss-Italian pharmacologist and academic, <a href=\"https://wikipedia.org/wiki/Nobel_Prize_in_Physiology_or_Medicine\" title=\"Nobel Prize in Physiology or Medicine\">Nobel Prize</a> laureate (b. 1907)"
        },
        {
            "year": 1993,
            "html": "<a href=\"https://wikipedia.org/wiki/Marian_Anderson\" title=\"Marian Anderson\">Marian Anderson</a>, American operatic singer (b. 1897)"
        },
        {
            "year": 1994,
            "html": "<a href=\"https://wikipedia.org/wiki/Fran%C3%A7ois_Rozet\" title=\"François Rozet\">François Rozet</a>, French-Canadian actor (b. 1899)"
        },
        {
            "year": 1996,
            "html": "<a href=\"https://wikipedia.org/wiki/Ben_Johnson_(actor)\" title=\"Ben Johnson (actor)\">Ben Johnson</a>, American actor and stuntman (b. 1918)"
        },
        {
            "year": 1996,
            "html": "<a href=\"https://wikipedia.org/wiki/Le%C3%B3n_Klimovsky\" title=\"León Klimovsky\">León Klimovsky</a>, Argentinian-Spanish actor, director, and screenwriter (b. 1906)"
        },
        {
            "year": 1996,
            "html": "<a href=\"https://wikipedia.org/wiki/Mick_Young\" title=\"Mick Young\">Mick Young</a>, Australian politician (b. 1936)"
        },
        {
            "year": 1997,
            "html": "<a href=\"https://wikipedia.org/wiki/Laura_Nyro\" title=\"Laura Nyro\">Laura Nyro</a>, American singer-songwriter and pianist (b. 1947)"
        },
        {
            "year": 2000,
            "html": "<a href=\"https://wikipedia.org/wiki/Franti%C5%A1ek_%C5%A0%C5%A5astn%C3%BD\" title=\"František Šťastný\">František Šťastný</a>, Czech motorcycle racer (b. 1927)"
        },
        {
            "year": 2000,
            "html": "<a href=\"https://wikipedia.org/wiki/Claire_Trevor\" title=\"Claire Trevor\">Claire Trevor</a>, American actress (b. 1910)"
        },
        {
            "year": 2002,
            "html": "<a href=\"https://wikipedia.org/wiki/Mar%C3%ADa_F%C3%A9lix\" title=\"María Félix\">María Félix</a>, Mexican actress (b. 1914)"
        },
        {
            "year": 2002,
            "html": "<a href=\"https://wikipedia.org/wiki/Harvey_Quaytman\" title=\"Harvey Quaytman\">Harvey Quaytman</a>, American painter (b. 1937)"
        },
        {
            "year": 2004,
            "html": "<a href=\"https://wikipedia.org/wiki/Werner_Schumacher\" title=\"Werner Schumacher\">Werner Schumacher</a>, German actor (b. 1921)"
        },
        {
            "year": 2005,
            "html": "<a href=\"https://wikipedia.org/wiki/Onna_White\" title=\"Onna White\">Onna White</a>, Canadian choreographer and dancer (b. 1922)"
        },
        {
            "year": 2006,
            "html": "<a href=\"https://wikipedia.org/wiki/Gerard_Reve\" title=\"Gerard Reve\">Gerard Reve</a>, Dutch author and poet (b. 1923)"
        },
        {
            "year": 2007,
            "html": "<a href=\"https://wikipedia.org/wiki/Sol_LeWitt\" title=\"Sol LeWitt\">Sol LeWitt</a>, American painter and sculptor (b. 1928)"
        },
        {
            "year": 2008,
            "html": "<a href=\"https://wikipedia.org/wiki/Kazuo_Shiraga\" title=\"Kazuo Shiraga\">Kazuo Shiraga</a>, Japanese painter (b. 1924)"
        },
        {
            "year": 2009,
            "html": "<a href=\"https://wikipedia.org/wiki/Richard_de_Mille\" title=\"Richard de Mille\">Richard de Mille</a>, American Scientologist, author, investigative journalist, and psychologist (b. 1922)"
        },
        {
            "year": 2009,
            "html": "<a href=\"https://wikipedia.org/wiki/Piotr_Morawski\" title=\"Piotr Morawski\">Piotr Morawski</a>, Polish mountaineer (b. 1976)"
        },
        {
            "year": 2010,
            "html": "<a href=\"https://wikipedia.org/wiki/Malcolm_McLaren\" title=\"Malcolm McLaren\">Malcolm McLaren</a>, English singer-songwriter (b. 1946)"
        },
        {
            "year": 2010,
            "html": "<a href=\"https://wikipedia.org/wiki/Teddy_Scholten\" title=\"Teddy Scholten\">Teddy Scholten</a>, Dutch singer (b. 1926)"
        },
        {
            "year": 2011,
            "html": "<a href=\"https://wikipedia.org/wiki/Hedda_Sterne\" title=\"Hedda Sterne\">Hedda Sterne</a>, Romanian-American painter and photographer (b. 1910)"
        },
        {
            "year": 2012,
            "html": "<a href=\"https://wikipedia.org/wiki/Blair_Kiel\" title=\"Blair Kiel\">Blair Kiel</a>, American football player and coach (b. 1961)"
        },
        {
            "year": 2012,
            "html": "<a href=\"https://wikipedia.org/wiki/Jack_Tramiel\" title=\"Jack Tramiel\">Jack Tramiel</a>, Polish-American businessman, founded <a href=\"https://wikipedia.org/wiki/Commodore_International\" title=\"Commodore International\">Commodore International</a> (b. 1928)"
        },
        {
            "year": 2012,
            "html": "<a href=\"https://wikipedia.org/wiki/Janusz_K._Zawodny\" title=\"Janusz K. Zawodny\">Janusz K. Zawodny</a>, Polish-American soldier, historian, and political scientist (b. 1921)"
        },
        {
            "year": 2013,
            "html": "<a href=\"https://wikipedia.org/wiki/Mikhail_Beketov\" title=\"Mikhail Beketov\">Mikhail Beketov</a>, Russian journalist (b. 1958)"
        },
        {
            "year": 2013,
            "html": "<a href=\"https://wikipedia.org/wiki/Annette_Funicello\" title=\"Annette Funicello\">Annette Funicello</a>, American actress and singer (b. 1942)"
        },
        {
            "year": 2013,
            "html": "<a href=\"https://wikipedia.org/wiki/Sara_Montiel\" title=\"Sara Montiel\">Sara Montiel</a>, Spanish-Mexican actress and singer (b. 1928)"
        },
        {
            "year": 2013,
            "html": "<a href=\"https://wikipedia.org/wiki/Jos%C3%A9_Luis_Sampedro\" title=\"José Luis Sampedro\">José Luis Sampedro</a>, Spanish economist and author (b. 1917)"
        },
        {
            "year": 2013,
            "html": "<a href=\"https://wikipedia.org/wiki/Margaret_Thatcher\" title=\"Margaret Thatcher\">Margaret Thatcher</a>, English politician, first female <a href=\"https://wikipedia.org/wiki/Prime_Minister_of_the_United_Kingdom\" title=\"Prime Minister of the United Kingdom\">Prime Minister of the United Kingdom</a> (b. 1925)"
        },
        {
            "year": 2014,
            "html": "<a href=\"https://wikipedia.org/wiki/Emmanuel_III_Delly\" title=\"Emmanuel III Delly\">Emmanuel III Delly</a>, Iraqi patriarch (b. 1927)"
        },
        {
            "year": 2014,
            "html": "<a href=\"https://wikipedia.org/wiki/Karlheinz_Deschner\" title=\"Karlheinz Deschner\">Karlheinz Deschner</a>, German author and activist (b. 1924)"
        },
        {
            "year": 2014,
            "html": "<a href=\"https://wikipedia.org/wiki/Ivan_Mercep\" title=\"Ivan Mercep\">Ivan Mercep</a>, New Zealand architect, designed the <a href=\"https://wikipedia.org/wiki/Museum_of_New_Zealand_Te_Papa_Tongarewa\" title=\"Museum of New Zealand Te Papa Tongarewa\">Te Papa Tongarewa Museum</a> (b. 1930)"
        },
        {
            "year": 2015,
            "html": "<a href=\"https://wikipedia.org/wiki/Jayakanthan\" title=\"Jayakanthan\">Jayakanthan</a>, Indian journalist and author (b. 1934)"
        },
        {
            "year": 2015,
            "html": "<a href=\"https://wikipedia.org/wiki/Rayson_Huang\" title=\"Rayson Huang\">Rayson Huang</a>, Hong Kong chemist and academic (b. 1920)"
        },
        {
            "year": 2015,
            "html": "<a href=\"https://wikipedia.org/wiki/Sergei_Lashchenko\" title=\"Sergei Lashchenko\">Sergei Lashchenko</a>, Ukrainian kick-boxer (b. 1987)"
        },
        {
            "year": 2015,
            "html": "<a href=\"https://wikipedia.org/wiki/David_Laventhol\" title=\"David Laventhol\">David Laventhol</a>, American journalist and publisher (b. 1933)"
        },
        {
            "year": 2015,
            "html": "<a href=\"https://wikipedia.org/wiki/Jean-Claude_Turcotte\" title=\"Jean-Claude Turcotte\">Jean-Claude Turcotte</a>, Canadian cardinal (b. 1936)"
        },
        {
            "year": 2019,
            "html": "<a href=\"https://wikipedia.org/wiki/Josine_Ianco-Starrels\" title=\"Josine Ianco-Starrels\">Josine Ianco-Starrels</a>, Romanian-born American art curator (b. 1926)"
        },
        {
            "year": 2020,
            "html": "<a href=\"https://wikipedia.org/wiki/Rick_May\" title=\"Rick May\">Rick May</a>, American-Canadian voice actor (b. 1940)"
        },
        {
            "year": 2020,
            "html": "<a href=\"https://wikipedia.org/wiki/Abdul_Momin_Imambari\" title=\"Abdul Momin Imambari\">Abdul Momin Imambari</a>, Bangladeshi Islamic scholar (b. 1930)"
        },
        {
            "year": 2022,
            "html": "<a href=\"https://wikipedia.org/wiki/Mimi_Reinhardt\" title=\"Mimi Reinhardt\">Mimi Reinhardt</a>, Austrian Jewish secretary (b. 1915)"
        }
    ]
}
